{".class":"MypyFile","_fullname":"pathvalidate.__version__","future_import_flags":[],"is_partial_stub_package":false,"is_stub":false,"names":{".class":"SymbolTable","Final":{".class":"SymbolTableNode","cross_ref":"typing.Final","kind":"Gdef"},"__annotations__":{".class":"SymbolTableNode","kind":"Gdef","node":{".class":"Var","flags":["is_ready"],"fullname":"pathvalidate.__version__.__annotations__","name":"__annotations__","setter_type":null,"type":{".class":"Instance","args":["builtins.str",{".class":"AnyType","missing_import_name":null,"source_any":null,"type_of_any":6}],"extra_attrs":null,"type_ref":"builtins.dict"}}},"__author__":{".class":"SymbolTableNode","kind":"Gdef","node":{".class":"Var","final_value":"Tsuyoshi Hombashi","flags":["is_final","is_ready","is_inferred","has_explicit_value"],"fullname":"pathvalidate.__version__.__author__","name":"__author__","setter_type":null,"type":{".class":"Instance","args":[],"extra_attrs":null,"last_known_value":{".class":"LiteralType","fallback":"builtins.str","value":"Tsuyoshi Hombashi"},"type_ref":"builtins.str"}}},"__copyright__":{".class":"SymbolTableNode","kind":"Gdef","node":{".class":"Var","flags":["is_final","is_ready","is_inferred","has_explicit_value"],"fullname":"pathvalidate.__version__.__copyright__","name":"__copyright__","setter_type":null,"type":"builtins.str"}},"__doc__":{".class":"SymbolTableNode","kind":"Gdef","node":{".class":"Var","flags":["is_ready"],"fullname":"pathvalidate.__version__.__doc__","name":"__doc__","setter_type":null,"type":"builtins.str"}},"__email__":{".class":"SymbolTableNode","kind":"Gdef","node":{".class":"Var","final_value":"tsuyoshi.hombashi@gmail.com","flags":["is_final","is_ready","is_inferred","has_explicit_value"],"fullname":"pathvalidate.__version__.__email__","name":"__email__","setter_type":null,"type":{".class":"Instance","args":[],"extra_attrs":null,"last_known_value":{".class":"LiteralType","fallback":"builtins.str","value":"tsuyoshi.hombashi@gmail.com"},"type_ref":"builtins.str"}}},"__file__":{".class":"SymbolTableNode","kind":"Gdef","node":{".class":"Var","flags":["is_ready"],"fullname":"pathvalidate.__version__.__file__","name":"__file__","setter_type":null,"type":"builtins.str"}},"__license__":{".class":"SymbolTableNode","kind":"Gdef","node":{".class":"Var","final_value":"MIT License","flags":["is_final","is_ready","is_inferred","has_explicit_value"],"fullname":"pathvalidate.__version__.__license__","name":"__license__","setter_type":null,"type":{".class":"Instance","args":[],"extra_attrs":null,"last_known_value":{".class":"LiteralType","fallback":"builtins.str","value":"MIT License"},"type_ref":"builtins.str"}}},"__maintainer__":{".class":"SymbolTableNode","kind":"Gdef","node":{".class":"Var","final_value":"Tsuyoshi Hombashi","flags":["is_final","is_ready","is_inferred","has_explicit_value"],"fullname":"pathvalidate.__version__.__maintainer__","name":"__maintainer__","setter_type":null,"type":{".class":"Instance","args":[],"extra_attrs":null,"last_known_value":{".class":"LiteralType","fallback":"builtins.str","value":"Tsuyoshi Hombashi"},"type_ref":"builtins.str"}}},"__name__":{".class":"SymbolTableNode","kind":"Gdef","node":{".class":"Var","flags":["is_ready"],"fullname":"pathvalidate.__version__.__name__","name":"__name__","setter_type":null,"type":"builtins.str"}},"__package__":{".class":"SymbolTableNode","kind":"Gdef","node":{".class":"Var","flags":["is_ready"],"fullname":"pathvalidate.__version__.__package__","name":"__package__","setter_type":null,"type":"builtins.str"}},"__spec__":{".class":"SymbolTableNode","kind":"Gdef","node":{".class":"Var","flags":["is_ready"],"fullname":"pathvalidate.__version__.__spec__","name":"__spec__","setter_type":null,"type":"_frozen_importlib.ModuleSpec"}},"__version__":{".class":"SymbolTableNode","kind":"Gdef","node":{".class":"Var","flags":["is_ready","is_inferred","has_explicit_value"],"fullname":"pathvalidate.__version__.__version__","name":"__version__","setter_type":null,"type":"builtins.str"}}},"path":"/home/ab916/src/clawbridge/.venv/lib/python3.13/site-packages/pathvalidate/__version__.py"}