{".class":"MypyFile","_fullname":"agno.vectordb.base","future_import_flags":[],"is_partial_stub_package":false,"is_stub":false,"names":{".class":"SymbolTable","ABC":{".class":"SymbolTableNode","cross_ref":"abc.ABC","kind":"Gdef"},"Any":{".class":"SymbolTableNode","cross_ref":"typing.Any","kind":"Gdef"},"Dict":{".class":"SymbolTableNode","cross_ref":"typing.Dict","kind":"Gdef"},"Document":{".class":"SymbolTableNode","cross_ref":"agno.knowledge.document.base.Document","kind":"Gdef"},"List":{".class":"SymbolTableNode","cross_ref":"typing.List","kind":"Gdef"},"Optional":{".class":"SymbolTableNode","cross_ref":"typing.Optional","kind":"Gdef"},"VectorDb":{".class":"SymbolTableNode","kind":"Gdef","node":{".class":"TypeInfo","_promote":[],"abstract_attributes":[["async_create",1],["async_drop",1],["async_exists",1],["async_insert",1],["async_name_exists",1],["async_search",1],["async_upsert",1],["content_hash_exists",1],["create",1],["delete",1],["delete_by_content_id",1],["delete_by_id",1],["delete_by_metadata",1],["delete_by_name",1],["drop",1],["exists",1],["get_supported_search_types",1],["id_exists",1],["insert",1],["name_exists",1],["search",1],["upsert",1]],"alt_promote":null,"bases":["abc.ABC"],"dataclass_transform_spec":null,"declared_metaclass":null,"defn":{".class":"ClassDef","fullname":"agno.vectordb.base.VectorDb","name":"VectorDb","type_vars":[]},"deletable_attributes":[],"deprecated":null,"flags":["is_abstract"],"fullname":"agno.vectordb.base.VectorDb","has_param_spec_type":false,"metaclass_type":"abc.ABCMeta","metadata":{},"module_name":"agno.vectordb.base","mro":["agno.vectordb.base.VectorDb","abc.ABC","builtins.object"],"names":{".class":"SymbolTable","__init__":{".class":"SymbolTableNode","kind":"Mdef","node":{".class":"FuncDef","abstract_status":0,"arg_kinds":[0,5,5,5,5],"arg_names":["self","id","name","description","similarity_threshold"],"dataclass_transform_spec":null,"deprecated":null,"flags":["is_trivial_self"],"fullname":"agno.vectordb.base.VectorDb.__init__","name":"__init__","original_first_arg":"self","type":{".class":"CallableType","arg_kinds":[0,5,5,5,5],"arg_names":["self","id","name","description","similarity_threshold"],"arg_types":["agno.vectordb.base.VectorDb",{".class":"UnionType","items":["builtins.str",{".class":"NoneType"}],"uses_pep604_syntax":false},{".class":"UnionType","items":["builtins.str",{".class":"NoneType"}],"uses_pep604_syntax":false},{".class":"UnionType","items":["builtins.str",{".class":"NoneType"}],"uses_pep604_syntax":false},{".class":"UnionType","items":["builtins.float",{".class":"NoneType"}],"uses_pep604_syntax":false}],"fallback":"builtins.function","from_concatenate":false,"implicit":false,"imprecise_arg_kinds":false,"is_bound":false,"is_ellipsis_args":false,"name":"__init__ of VectorDb","ret_type":{".class":"NoneType"},"type_guard":null,"type_is":null,"unpack_kwargs":false,"variables":[]}}},"async_create":{".class":"SymbolTableNode","kind":"Mdef","node":{".class":"Decorator","func":{".class":"FuncDef","abstract_status":1,"arg_kinds":[0],"arg_names":["self"],"dataclass_transform_spec":null,"deprecated":null,"flags":["is_coroutine","is_decorated","is_trivial_body","is_trivial_self"],"fullname":"agno.vectordb.base.VectorDb.async_create","name":"async_create","original_first_arg":"self","type":{".class":"CallableType","arg_kinds":[0],"arg_names":["self"],"arg_types":["agno.vectordb.base.VectorDb"],"fallback":"builtins.function","from_concatenate":false,"implicit":false,"imprecise_arg_kinds":false,"is_bound":false,"is_ellipsis_args":false,"name":"async_create of VectorDb","ret_type":{".class":"Instance","args":[{".class":"AnyType","missing_import_name":null,"source_any":null,"type_of_any":6},{".class":"AnyType","missing_import_name":null,"source_any":null,"type_of_any":6},{".class":"NoneType"}],"extra_attrs":null,"type_ref":"typing.Coroutine"},"type_guard":null,"type_is":null,"unpack_kwargs":false,"variables":[]}},"is_overload":false,"var":{".class":"Var","flags":["is_initialized_in_class","is_ready","is_inferred"],"fullname":"agno.vectordb.base.VectorDb.async_create","name":"async_create","setter_type":null,"type":{".class":"CallableType","arg_kinds":[0],"arg_names":["self"],"arg_types":["agno.vectordb.base.VectorDb"],"fallback":"builtins.function","from_concatenate":false,"implicit":false,"imprecise_arg_kinds":false,"is_bound":false,"is_ellipsis_args":false,"name":"async_create of VectorDb","ret_type":{".class":"Instance","args":[{".class":"AnyType","missing_import_name":null,"source_any":null,"type_of_any":6},{".class":"AnyType","missing_import_name":null,"source_any":null,"type_of_any":6},{".class":"NoneType"}],"extra_attrs":null,"type_ref":"typing.Coroutine"},"type_guard":null,"type_is":null,"unpack_kwargs":false,"variables":[]}}}},"async_drop":{".class":"SymbolTableNode","kind":"Mdef","node":{".class":"Decorator","func":{".class":"FuncDef","abstract_status":1,"arg_kinds":[0],"arg_names":["self"],"dataclass_transform_spec":null,"deprecated":null,"flags":["is_coroutine","is_decorated","is_trivial_body","is_trivial_self"],"fullname":"agno.vectordb.base.VectorDb.async_drop","name":"async_drop","original_first_arg":"self","type":{".class":"CallableType","arg_kinds":[0],"arg_names":["self"],"arg_types":["agno.vectordb.base.VectorDb"],"fallback":"builtins.function","from_concatenate":false,"implicit":false,"imprecise_arg_kinds":false,"is_bound":false,"is_ellipsis_args":false,"name":"async_drop of VectorDb","ret_type":{".class":"Instance","args":[{".class":"AnyType","missing_import_name":null,"source_any":null,"type_of_any":6},{".class":"AnyType","missing_import_name":null,"source_any":null,"type_of_any":6},{".class":"NoneType"}],"extra_attrs":null,"type_ref":"typing.Coroutine"},"type_guard":null,"type_is":null,"unpack_kwargs":false,"variables":[]}},"is_overload":false,"var":{".class":"Var","flags":["is_initialized_in_class","is_ready","is_inferred"],"fullname":"agno.vectordb.base.VectorDb.async_drop","name":"async_drop","setter_type":null,"type":{".class":"CallableType","arg_kinds":[0],"arg_names":["self"],"arg_types":["agno.vectordb.base.VectorDb"],"fallback":"builtins.function","from_concatenate":false,"implicit":false,"imprecise_arg_kinds":false,"is_bound":false,"is_ellipsis_args":false,"name":"async_drop of VectorDb","ret_type":{".class":"Instance","args":[{".class":"AnyType","missing_import_name":null,"source_any":null,"type_of_any":6},{".class":"AnyType","missing_import_name":null,"source_any":null,"type_of_any":6},{".class":"NoneType"}],"extra_attrs":null,"type_ref":"typing.Coroutine"},"type_guard":null,"type_is":null,"unpack_kwargs":false,"variables":[]}}}},"async_exists":{".class":"SymbolTableNode","kind":"Mdef","node":{".class":"Decorator","func":{".class":"FuncDef","abstract_status":1,"arg_kinds":[0],"arg_names":["self"],"dataclass_transform_spec":null,"deprecated":null,"flags":["is_coroutine","is_decorated","is_trivial_body","is_trivial_self"],"fullname":"agno.vectordb.base.VectorDb.async_exists","name":"async_exists","original_first_arg":"self","type":{".class":"CallableType","arg_kinds":[0],"arg_names":["self"],"arg_types":["agno.vectordb.base.VectorDb"],"fallback":"builtins.function","from_concatenate":false,"implicit":false,"imprecise_arg_kinds":false,"is_bound":false,"is_ellipsis_args":false,"name":"async_exists of VectorDb","ret_type":{".class":"Instance","args":[{".class":"AnyType","missing_import_name":null,"source_any":null,"type_of_any":6},{".class":"AnyType","missing_import_name":null,"source_any":null,"type_of_any":6},"builtins.bool"],"extra_attrs":null,"type_ref":"typing.Coroutine"},"type_guard":null,"type_is":null,"unpack_kwargs":false,"variables":[]}},"is_overload":false,"var":{".class":"Var","flags":["is_initialized_in_class","is_ready","is_inferred"],"fullname":"agno.vectordb.base.VectorDb.async_exists","name":"async_exists","setter_type":null,"type":{".class":"CallableType","arg_kinds":[0],"arg_names":["self"],"arg_types":["agno.vectordb.base.VectorDb"],"fallback":"builtins.function","from_concatenate":false,"implicit":false,"imprecise_arg_kinds":false,"is_bound":false,"is_ellipsis_args":false,"name":"async_exists of VectorDb","ret_type":{".class":"Instance","args":[{".class":"AnyType","missing_import_name":null,"source_any":null,"type_of_any":6},{".class":"AnyType","missing_import_name":null,"source_any":null,"type_of_any":6},"builtins.bool"],"extra_attrs":null,"type_ref":"typing.Coroutine"},"type_guard":null,"type_is":null,"unpack_kwargs":false,"variables":[]}}}},"async_insert":{".class":"SymbolTableNode","kind":"Mdef","node":{".class":"Decorator","func":{".class":"FuncDef","abstract_status":1,"arg_kinds":[0,0,0,1],"arg_names":["self","content_hash","documents","filters"],"dataclass_transform_spec":null,"deprecated":null,"flags":["is_coroutine","is_decorated","is_trivial_body","is_trivial_self"],"fullname":"agno.vectordb.base.VectorDb.async_insert","name":"async_insert","original_first_arg":"self","type":{".class":"CallableType","arg_kinds":[0,0,0,1],"arg_names":["self","content_hash","documents","filters"],"arg_types":["agno.vectordb.base.VectorDb","builtins.str",{".class":"Instance","args":["agno.knowledge.document.base.Document"],"extra_attrs":null,"type_ref":"builtins.list"},{".class":"UnionType","items":[{".class":"Instance","args":["builtins.str",{".class":"AnyType","missing_import_name":null,"source_any":null,"type_of_any":2}],"extra_attrs":null,"type_ref":"builtins.dict"},{".class":"NoneType"}],"uses_pep604_syntax":false}],"fallback":"builtins.function","from_concatenate":false,"implicit":false,"imprecise_arg_kinds":false,"is_bound":false,"is_ellipsis_args":false,"name":"async_insert of VectorDb","ret_type":{".class":"Instance","args":[{".class":"AnyType","missing_import_name":null,"source_any":null,"type_of_any":6},{".class":"AnyType","missing_import_name":null,"source_any":null,"type_of_any":6},{".class":"NoneType"}],"extra_attrs":null,"type_ref":"typing.Coroutine"},"type_guard":null,"type_is":null,"unpack_kwargs":false,"variables":[]}},"is_overload":false,"var":{".class":"Var","flags":["is_initialized_in_class","is_ready","is_inferred"],"fullname":"agno.vectordb.base.VectorDb.async_insert","name":"async_insert","setter_type":null,"type":{".class":"CallableType","arg_kinds":[0,0,0,1],"arg_names":["self","content_hash","documents","filters"],"arg_types":["agno.vectordb.base.VectorDb","builtins.str",{".class":"Instance","args":["agno.knowledge.document.base.Document"],"extra_attrs":null,"type_ref":"builtins.list"},{".class":"UnionType","items":[{".class":"Instance","args":["builtins.str",{".class":"AnyType","missing_import_name":null,"source_any":null,"type_of_any":2}],"extra_attrs":null,"type_ref":"builtins.dict"},{".class":"NoneType"}],"uses_pep604_syntax":false}],"fallback":"builtins.function","from_concatenate":false,"implicit":false,"imprecise_arg_kinds":false,"is_bound":false,"is_ellipsis_args":false,"name":"async_insert of VectorDb","ret_type":{".class":"Instance","args":[{".class":"AnyType","missing_import_name":null,"source_any":null,"type_of_any":6},{".class":"AnyType","missing_import_name":null,"source_any":null,"type_of_any":6},{".class":"NoneType"}],"extra_attrs":null,"type_ref":"typing.Coroutine"},"type_guard":null,"type_is":null,"unpack_kwargs":false,"variables":[]}}}},"async_name_exists":{".class":"SymbolTableNode","kind":"Mdef","node":{".class":"Decorator","func":{".class":"FuncDef","abstract_status":1,"arg_kinds":[0,0],"arg_names":["self","name"],"dataclass_transform_spec":null,"deprecated":null,"flags":["is_decorated","is_trivial_body","is_trivial_self"],"fullname":"agno.vectordb.base.VectorDb.async_name_exists","name":"async_name_exists","original_first_arg":"self","type":{".class":"CallableType","arg_kinds":[0,0],"arg_names":["self","name"],"arg_types":["agno.vectordb.base.VectorDb","builtins.str"],"fallback":"builtins.function","from_concatenate":false,"implicit":false,"imprecise_arg_kinds":false,"is_bound":false,"is_ellipsis_args":false,"name":"async_name_exists of VectorDb","ret_type":"builtins.bool","type_guard":null,"type_is":null,"unpack_kwargs":false,"variables":[]}},"is_overload":false,"var":{".class":"Var","flags":["is_initialized_in_class","is_ready","is_inferred"],"fullname":"agno.vectordb.base.VectorDb.async_name_exists","name":"async_name_exists","setter_type":null,"type":{".class":"CallableType","arg_kinds":[0,0],"arg_names":["self","name"],"arg_types":["agno.vectordb.base.VectorDb","builtins.str"],"fallback":"builtins.function","from_concatenate":false,"implicit":false,"imprecise_arg_kinds":false,"is_bound":false,"is_ellipsis_args":false,"name":"async_name_exists of VectorDb","ret_type":"builtins.bool","type_guard":null,"type_is":null,"unpack_kwargs":false,"variables":[]}}}},"async_search":{".class":"SymbolTableNode","kind":"Mdef","node":{".class":"Decorator","func":{".class":"FuncDef","abstract_status":1,"arg_kinds":[0,0,1,1],"arg_names":["self","query","limit","filters"],"dataclass_transform_spec":null,"deprecated":null,"flags":["is_coroutine","is_decorated","is_trivial_body","is_trivial_self"],"fullname":"agno.vectordb.base.VectorDb.async_search","name":"async_search","original_first_arg":"self","type":{".class":"CallableType","arg_kinds":[0,0,1,1],"arg_names":["self","query","limit","filters"],"arg_types":["agno.vectordb.base.VectorDb","builtins.str","builtins.int",{".class":"UnionType","items":[{".class":"AnyType","missing_import_name":null,"source_any":null,"type_of_any":2},{".class":"NoneType"}],"uses_pep604_syntax":false}],"fallback":"builtins.function","from_concatenate":false,"implicit":false,"imprecise_arg_kinds":false,"is_bound":false,"is_ellipsis_args":false,"name":"async_search of VectorDb","ret_type":{".class":"Instance","args":[{".class":"AnyType","missing_import_name":null,"source_any":null,"type_of_any":6},{".class":"AnyType","missing_import_name":null,"source_any":null,"type_of_any":6},{".class":"Instance","args":["agno.knowledge.document.base.Document"],"extra_attrs":null,"type_ref":"builtins.list"}],"extra_attrs":null,"type_ref":"typing.Coroutine"},"type_guard":null,"type_is":null,"unpack_kwargs":false,"variables":[]}},"is_overload":false,"var":{".class":"Var","flags":["is_initialized_in_class","is_ready","is_inferred"],"fullname":"agno.vectordb.base.VectorDb.async_search","name":"async_search","setter_type":null,"type":{".class":"CallableType","arg_kinds":[0,0,1,1],"arg_names":["self","query","limit","filters"],"arg_types":["agno.vectordb.base.VectorDb","builtins.str","builtins.int",{".class":"UnionType","items":[{".class":"AnyType","missing_import_name":null,"source_any":null,"type_of_any":2},{".class":"NoneType"}],"uses_pep604_syntax":false}],"fallback":"builtins.function","from_concatenate":false,"implicit":false,"imprecise_arg_kinds":false,"is_bound":false,"is_ellipsis_args":false,"name":"async_search of VectorDb","ret_type":{".class":"Instance","args":[{".class":"AnyType","missing_import_name":null,"source_any":null,"type_of_any":6},{".class":"AnyType","missing_import_name":null,"source_any":null,"type_of_any":6},{".class":"Instance","args":["agno.knowledge.document.base.Document"],"extra_attrs":null,"type_ref":"builtins.list"}],"extra_attrs":null,"type_ref":"typing.Coroutine"},"type_guard":null,"type_is":null,"unpack_kwargs":false,"variables":[]}}}},"async_upsert":{".class":"SymbolTableNode","kind":"Mdef","node":{".class":"Decorator","func":{".class":"FuncDef","abstract_status":1,"arg_kinds":[0,0,0,1],"arg_names":["self","content_hash","documents","filters"],"dataclass_transform_spec":null,"deprecated":null,"flags":["is_coroutine","is_decorated","is_trivial_body","is_trivial_self"],"fullname":"agno.vectordb.base.VectorDb.async_upsert","name":"async_upsert","original_first_arg":"self","type":{".class":"CallableType","arg_kinds":[0,0,0,1],"arg_names":["self","content_hash","documents","filters"],"arg_types":["agno.vectordb.base.VectorDb","builtins.str",{".class":"Instance","args":["agno.knowledge.document.base.Document"],"extra_attrs":null,"type_ref":"builtins.list"},{".class":"UnionType","items":[{".class":"Instance","args":["builtins.str",{".class":"AnyType","missing_import_name":null,"source_any":null,"type_of_any":2}],"extra_attrs":null,"type_ref":"builtins.dict"},{".class":"NoneType"}],"uses_pep604_syntax":false}],"fallback":"builtins.function","from_concatenate":false,"implicit":false,"imprecise_arg_kinds":false,"is_bound":false,"is_ellipsis_args":false,"name":"async_upsert of VectorDb","ret_type":{".class":"Instance","args":[{".class":"AnyType","missing_import_name":null,"source_any":null,"type_of_any":6},{".class":"AnyType","missing_import_name":null,"source_any":null,"type_of_any":6},{".class":"NoneType"}],"extra_attrs":null,"type_ref":"typing.Coroutine"},"type_guard":null,"type_is":null,"unpack_kwargs":false,"variables":[]}},"is_overload":false,"var":{".class":"Var","flags":["is_initialized_in_class","is_ready","is_inferred"],"fullname":"agno.vectordb.base.VectorDb.async_upsert","name":"async_upsert","setter_type":null,"type":{".class":"CallableType","arg_kinds":[0,0,0,1],"arg_names":["self","content_hash","documents","filters"],"arg_types":["agno.vectordb.base.VectorDb","builtins.str",{".class":"Instance","args":["agno.knowledge.document.base.Document"],"extra_attrs":null,"type_ref":"builtins.list"},{".class":"UnionType","items":[{".class":"Instance","args":["builtins.str",{".class":"AnyType","missing_import_name":null,"source_any":null,"type_of_any":2}],"extra_attrs":null,"type_ref":"builtins.dict"},{".class":"NoneType"}],"uses_pep604_syntax":false}],"fallback":"builtins.function","from_concatenate":false,"implicit":false,"imprecise_arg_kinds":false,"is_bound":false,"is_ellipsis_args":false,"name":"async_upsert of VectorDb","ret_type":{".class":"Instance","args":[{".class":"AnyType","missing_import_name":null,"source_any":null,"type_of_any":6},{".class":"AnyType","missing_import_name":null,"source_any":null,"type_of_any":6},{".class":"NoneType"}],"extra_attrs":null,"type_ref":"typing.Coroutine"},"type_guard":null,"type_is":null,"unpack_kwargs":false,"variables":[]}}}},"content_hash_exists":{".class":"SymbolTableNode","kind":"Mdef","node":{".class":"Decorator","func":{".class":"FuncDef","abstract_status":1,"arg_kinds":[0,0],"arg_names":["self","content_hash"],"dataclass_transform_spec":null,"deprecated":null,"flags":["is_decorated","is_trivial_body","is_trivial_self"],"fullname":"agno.vectordb.base.VectorDb.content_hash_exists","name":"content_hash_exists","original_first_arg":"self","type":{".class":"CallableType","arg_kinds":[0,0],"arg_names":["self","content_hash"],"arg_types":["agno.vectordb.base.VectorDb","builtins.str"],"fallback":"builtins.function","from_concatenate":false,"implicit":false,"imprecise_arg_kinds":false,"is_bound":false,"is_ellipsis_args":false,"name":"content_hash_exists of VectorDb","ret_type":"builtins.bool","type_guard":null,"type_is":null,"unpack_kwargs":false,"variables":[]}},"is_overload":false,"var":{".class":"Var","flags":["is_initialized_in_class","is_ready","is_inferred"],"fullname":"agno.vectordb.base.VectorDb.content_hash_exists","name":"content_hash_exists","setter_type":null,"type":{".class":"CallableType","arg_kinds":[0,0],"arg_names":["self","content_hash"],"arg_types":["agno.vectordb.base.VectorDb","builtins.str"],"fallback":"builtins.function","from_concatenate":false,"implicit":false,"imprecise_arg_kinds":false,"is_bound":false,"is_ellipsis_args":false,"name":"content_hash_exists of VectorDb","ret_type":"builtins.bool","type_guard":null,"type_is":null,"unpack_kwargs":false,"variables":[]}}}},"create":{".class":"SymbolTableNode","kind":"Mdef","node":{".class":"Decorator","func":{".class":"FuncDef","abstract_status":1,"arg_kinds":[0],"arg_names":["self"],"dataclass_transform_spec":null,"deprecated":null,"flags":["is_decorated","is_trivial_body","is_trivial_self"],"fullname":"agno.vectordb.base.VectorDb.create","name":"create","original_first_arg":"self","type":{".class":"CallableType","arg_kinds":[0],"arg_names":["self"],"arg_types":["agno.vectordb.base.VectorDb"],"fallback":"builtins.function","from_concatenate":false,"implicit":false,"imprecise_arg_kinds":false,"is_bound":false,"is_ellipsis_args":false,"name":"create of VectorDb","ret_type":{".class":"NoneType"},"type_guard":null,"type_is":null,"unpack_kwargs":false,"variables":[]}},"is_overload":false,"var":{".class":"Var","flags":["is_initialized_in_class","is_ready","is_inferred"],"fullname":"agno.vectordb.base.VectorDb.create","name":"create","setter_type":null,"type":{".class":"CallableType","arg_kinds":[0],"arg_names":["self"],"arg_types":["agno.vectordb.base.VectorDb"],"fallback":"builtins.function","from_concatenate":false,"implicit":false,"imprecise_arg_kinds":false,"is_bound":false,"is_ellipsis_args":false,"name":"create of VectorDb","ret_type":{".class":"NoneType"},"type_guard":null,"type_is":null,"unpack_kwargs":false,"variables":[]}}}},"delete":{".class":"SymbolTableNode","kind":"Mdef","node":{".class":"Decorator","func":{".class":"FuncDef","abstract_status":1,"arg_kinds":[0],"arg_names":["self"],"dataclass_transform_spec":null,"deprecated":null,"flags":["is_decorated","is_trivial_body","is_trivial_self"],"fullname":"agno.vectordb.base.VectorDb.delete","name":"delete","original_first_arg":"self","type":{".class":"CallableType","arg_kinds":[0],"arg_names":["self"],"arg_types":["agno.vectordb.base.VectorDb"],"fallback":"builtins.function","from_concatenate":false,"implicit":false,"imprecise_arg_kinds":false,"is_bound":false,"is_ellipsis_args":false,"name":"delete of VectorDb","ret_type":"builtins.bool","type_guard":null,"type_is":null,"unpack_kwargs":false,"variables":[]}},"is_overload":false,"var":{".class":"Var","flags":["is_initialized_in_class","is_ready","is_inferred"],"fullname":"agno.vectordb.base.VectorDb.delete","name":"delete","setter_type":null,"type":{".class":"CallableType","arg_kinds":[0],"arg_names":["self"],"arg_types":["agno.vectordb.base.VectorDb"],"fallback":"builtins.function","from_concatenate":false,"implicit":false,"imprecise_arg_kinds":false,"is_bound":false,"is_ellipsis_args":false,"name":"delete of VectorDb","ret_type":"builtins.bool","type_guard":null,"type_is":null,"unpack_kwargs":false,"variables":[]}}}},"delete_by_content_id":{".class":"SymbolTableNode","kind":"Mdef","node":{".class":"Decorator","func":{".class":"FuncDef","abstract_status":1,"arg_kinds":[0,0],"arg_names":["self","content_id"],"dataclass_transform_spec":null,"deprecated":null,"flags":["is_decorated","is_trivial_body","is_trivial_self"],"fullname":"agno.vectordb.base.VectorDb.delete_by_content_id","name":"delete_by_content_id","original_first_arg":"self","type":{".class":"CallableType","arg_kinds":[0,0],"arg_names":["self","content_id"],"arg_types":["agno.vectordb.base.VectorDb","builtins.str"],"fallback":"builtins.function","from_concatenate":false,"implicit":false,"imprecise_arg_kinds":false,"is_bound":false,"is_ellipsis_args":false,"name":"delete_by_content_id of VectorDb","ret_type":"builtins.bool","type_guard":null,"type_is":null,"unpack_kwargs":false,"variables":[]}},"is_overload":false,"var":{".class":"Var","flags":["is_initialized_in_class","is_ready","is_inferred"],"fullname":"agno.vectordb.base.VectorDb.delete_by_content_id","name":"delete_by_content_id","setter_type":null,"type":{".class":"CallableType","arg_kinds":[0,0],"arg_names":["self","content_id"],"arg_types":["agno.vectordb.base.VectorDb","builtins.str"],"fallback":"builtins.function","from_concatenate":false,"implicit":false,"imprecise_arg_kinds":false,"is_bound":false,"is_ellipsis_args":false,"name":"delete_by_content_id of VectorDb","ret_type":"builtins.bool","type_guard":null,"type_is":null,"unpack_kwargs":false,"variables":[]}}}},"delete_by_id":{".class":"SymbolTableNode","kind":"Mdef","node":{".class":"Decorator","func":{".class":"FuncDef","abstract_status":1,"arg_kinds":[0,0],"arg_names":["self","id"],"dataclass_transform_spec":null,"deprecated":null,"flags":["is_decorated","is_trivial_body","is_trivial_self"],"fullname":"agno.vectordb.base.VectorDb.delete_by_id","name":"delete_by_id","original_first_arg":"self","type":{".class":"CallableType","arg_kinds":[0,0],"arg_names":["self","id"],"arg_types":["agno.vectordb.base.VectorDb","builtins.str"],"fallback":"builtins.function","from_concatenate":false,"implicit":false,"imprecise_arg_kinds":false,"is_bound":false,"is_ellipsis_args":false,"name":"delete_by_id of VectorDb","ret_type":"builtins.bool","type_guard":null,"type_is":null,"unpack_kwargs":false,"variables":[]}},"is_overload":false,"var":{".class":"Var","flags":["is_initialized_in_class","is_ready","is_inferred"],"fullname":"agno.vectordb.base.VectorDb.delete_by_id","name":"delete_by_id","setter_type":null,"type":{".class":"CallableType","arg_kinds":[0,0],"arg_names":["self","id"],"arg_types":["agno.vectordb.base.VectorDb","builtins.str"],"fallback":"builtins.function","from_concatenate":false,"implicit":false,"imprecise_arg_kinds":false,"is_bound":false,"is_ellipsis_args":false,"name":"delete_by_id of VectorDb","ret_type":"builtins.bool","type_guard":null,"type_is":null,"unpack_kwargs":false,"variables":[]}}}},"delete_by_metadata":{".class":"SymbolTableNode","kind":"Mdef","node":{".class":"Decorator","func":{".class":"FuncDef","abstract_status":1,"arg_kinds":[0,0],"arg_names":["self","metadata"],"dataclass_transform_spec":null,"deprecated":null,"flags":["is_decorated","is_trivial_body","is_trivial_self"],"fullname":"agno.vectordb.base.VectorDb.delete_by_metadata","name":"delete_by_metadata","original_first_arg":"self","type":{".class":"CallableType","arg_kinds":[0,0],"arg_names":["self","metadata"],"arg_types":["agno.vectordb.base.VectorDb",{".class":"Instance","args":["builtins.str",{".class":"AnyType","missing_import_name":null,"source_any":null,"type_of_any":2}],"extra_attrs":null,"type_ref":"builtins.dict"}],"fallback":"builtins.function","from_concatenate":false,"implicit":false,"imprecise_arg_kinds":false,"is_bound":false,"is_ellipsis_args":false,"name":"delete_by_metadata of VectorDb","ret_type":"builtins.bool","type_guard":null,"type_is":null,"unpack_kwargs":false,"variables":[]}},"is_overload":false,"var":{".class":"Var","flags":["is_initialized_in_class","is_ready","is_inferred"],"fullname":"agno.vectordb.base.VectorDb.delete_by_metadata","name":"delete_by_metadata","setter_type":null,"type":{".class":"CallableType","arg_kinds":[0,0],"arg_names":["self","metadata"],"arg_types":["agno.vectordb.base.VectorDb",{".class":"Instance","args":["builtins.str",{".class":"AnyType","missing_import_name":null,"source_any":null,"type_of_any":2}],"extra_attrs":null,"type_ref":"builtins.dict"}],"fallback":"builtins.function","from_concatenate":false,"implicit":false,"imprecise_arg_kinds":false,"is_bound":false,"is_ellipsis_args":false,"name":"delete_by_metadata of VectorDb","ret_type":"builtins.bool","type_guard":null,"type_is":null,"unpack_kwargs":false,"variables":[]}}}},"delete_by_name":{".class":"SymbolTableNode","kind":"Mdef","node":{".class":"Decorator","func":{".class":"FuncDef","abstract_status":1,"arg_kinds":[0,0],"arg_names":["self","name"],"dataclass_transform_spec":null,"deprecated":null,"flags":["is_decorated","is_trivial_body","is_trivial_self"],"fullname":"agno.vectordb.base.VectorDb.delete_by_name","name":"delete_by_name","original_first_arg":"self","type":{".class":"CallableType","arg_kinds":[0,0],"arg_names":["self","name"],"arg_types":["agno.vectordb.base.VectorDb","builtins.str"],"fallback":"builtins.function","from_concatenate":false,"implicit":false,"imprecise_arg_kinds":false,"is_bound":false,"is_ellipsis_args":false,"name":"delete_by_name of VectorDb","ret_type":"builtins.bool","type_guard":null,"type_is":null,"unpack_kwargs":false,"variables":[]}},"is_overload":false,"var":{".class":"Var","flags":["is_initialized_in_class","is_ready","is_inferred"],"fullname":"agno.vectordb.base.VectorDb.delete_by_name","name":"delete_by_name","setter_type":null,"type":{".class":"CallableType","arg_kinds":[0,0],"arg_names":["self","name"],"arg_types":["agno.vectordb.base.VectorDb","builtins.str"],"fallback":"builtins.function","from_concatenate":false,"implicit":false,"imprecise_arg_kinds":false,"is_bound":false,"is_ellipsis_args":false,"name":"delete_by_name of VectorDb","ret_type":"builtins.bool","type_guard":null,"type_is":null,"unpack_kwargs":false,"variables":[]}}}},"description":{".class":"SymbolTableNode","implicit":true,"kind":"Mdef","node":{".class":"Var","flags":["is_ready","is_inferred"],"fullname":"agno.vectordb.base.VectorDb.description","name":"description","setter_type":null,"type":{".class":"UnionType","items":["builtins.str",{".class":"NoneType"}],"uses_pep604_syntax":false}}},"drop":{".class":"SymbolTableNode","kind":"Mdef","node":{".class":"Decorator","func":{".class":"FuncDef","abstract_status":1,"arg_kinds":[0],"arg_names":["self"],"dataclass_transform_spec":null,"deprecated":null,"flags":["is_decorated","is_trivial_body","is_trivial_self"],"fullname":"agno.vectordb.base.VectorDb.drop","name":"drop","original_first_arg":"self","type":{".class":"CallableType","arg_kinds":[0],"arg_names":["self"],"arg_types":["agno.vectordb.base.VectorDb"],"fallback":"builtins.function","from_concatenate":false,"implicit":false,"imprecise_arg_kinds":false,"is_bound":false,"is_ellipsis_args":false,"name":"drop of VectorDb","ret_type":{".class":"NoneType"},"type_guard":null,"type_is":null,"unpack_kwargs":false,"variables":[]}},"is_overload":false,"var":{".class":"Var","flags":["is_initialized_in_class","is_ready","is_inferred"],"fullname":"agno.vectordb.base.VectorDb.drop","name":"drop","setter_type":null,"type":{".class":"CallableType","arg_kinds":[0],"arg_names":["self"],"arg_types":["agno.vectordb.base.VectorDb"],"fallback":"builtins.function","from_concatenate":false,"implicit":false,"imprecise_arg_kinds":false,"is_bound":false,"is_ellipsis_args":false,"name":"drop of VectorDb","ret_type":{".class":"NoneType"},"type_guard":null,"type_is":null,"unpack_kwargs":false,"variables":[]}}}},"exists":{".class":"SymbolTableNode","kind":"Mdef","node":{".class":"Decorator","func":{".class":"FuncDef","abstract_status":1,"arg_kinds":[0],"arg_names":["self"],"dataclass_transform_spec":null,"deprecated":null,"flags":["is_decorated","is_trivial_body","is_trivial_self"],"fullname":"agno.vectordb.base.VectorDb.exists","name":"exists","original_first_arg":"self","type":{".class":"CallableType","arg_kinds":[0],"arg_names":["self"],"arg_types":["agno.vectordb.base.VectorDb"],"fallback":"builtins.function","from_concatenate":false,"implicit":false,"imprecise_arg_kinds":false,"is_bound":false,"is_ellipsis_args":false,"name":"exists of VectorDb","ret_type":"builtins.bool","type_guard":null,"type_is":null,"unpack_kwargs":false,"variables":[]}},"is_overload":false,"var":{".class":"Var","flags":["is_initialized_in_class","is_ready","is_inferred"],"fullname":"agno.vectordb.base.VectorDb.exists","name":"exists","setter_type":null,"type":{".class":"CallableType","arg_kinds":[0],"arg_names":["self"],"arg_types":["agno.vectordb.base.VectorDb"],"fallback":"builtins.function","from_concatenate":false,"implicit":false,"imprecise_arg_kinds":false,"is_bound":false,"is_ellipsis_args":false,"name":"exists of VectorDb","ret_type":"builtins.bool","type_guard":null,"type_is":null,"unpack_kwargs":false,"variables":[]}}}},"get_supported_search_types":{".class":"SymbolTableNode","kind":"Mdef","node":{".class":"Decorator","func":{".class":"FuncDef","abstract_status":1,"arg_kinds":[0],"arg_names":["self"],"dataclass_transform_spec":null,"deprecated":null,"flags":["is_decorated","is_trivial_body","is_trivial_self"],"fullname":"agno.vectordb.base.VectorDb.get_supported_search_types","name":"get_supported_search_types","original_first_arg":"self","type":{".class":"CallableType","arg_kinds":[0],"arg_names":["self"],"arg_types":["agno.vectordb.base.VectorDb"],"fallback":"builtins.function","from_concatenate":false,"implicit":false,"imprecise_arg_kinds":false,"is_bound":false,"is_ellipsis_args":false,"name":"get_supported_search_types of VectorDb","ret_type":{".class":"Instance","args":["builtins.str"],"extra_attrs":null,"type_ref":"builtins.list"},"type_guard":null,"type_is":null,"unpack_kwargs":false,"variables":[]}},"is_overload":false,"var":{".class":"Var","flags":["is_initialized_in_class","is_ready","is_inferred"],"fullname":"agno.vectordb.base.VectorDb.get_supported_search_types","name":"get_supported_search_types","setter_type":null,"type":{".class":"CallableType","arg_kinds":[0],"arg_names":["self"],"arg_types":["agno.vectordb.base.VectorDb"],"fallback":"builtins.function","from_concatenate":false,"implicit":false,"imprecise_arg_kinds":false,"is_bound":false,"is_ellipsis_args":false,"name":"get_supported_search_types of VectorDb","ret_type":{".class":"Instance","args":["builtins.str"],"extra_attrs":null,"type_ref":"builtins.list"},"type_guard":null,"type_is":null,"unpack_kwargs":false,"variables":[]}}}},"id":{".class":"SymbolTableNode","implicit":true,"kind":"Mdef","node":{".class":"Var","flags":["is_ready","is_inferred"],"fullname":"agno.vectordb.base.VectorDb.id","name":"id","setter_type":null,"type":"builtins.str"}},"id_exists":{".class":"SymbolTableNode","kind":"Mdef","node":{".class":"Decorator","func":{".class":"FuncDef","abstract_status":1,"arg_kinds":[0,0],"arg_names":["self","id"],"dataclass_transform_spec":null,"deprecated":null,"flags":["is_decorated","is_trivial_body","is_trivial_self"],"fullname":"agno.vectordb.base.VectorDb.id_exists","name":"id_exists","original_first_arg":"self","type":{".class":"CallableType","arg_kinds":[0,0],"arg_names":["self","id"],"arg_types":["agno.vectordb.base.VectorDb","builtins.str"],"fallback":"builtins.function","from_concatenate":false,"implicit":false,"imprecise_arg_kinds":false,"is_bound":false,"is_ellipsis_args":false,"name":"id_exists of VectorDb","ret_type":"builtins.bool","type_guard":null,"type_is":null,"unpack_kwargs":false,"variables":[]}},"is_overload":false,"var":{".class":"Var","flags":["is_initialized_in_class","is_ready","is_inferred"],"fullname":"agno.vectordb.base.VectorDb.id_exists","name":"id_exists","setter_type":null,"type":{".class":"CallableType","arg_kinds":[0,0],"arg_names":["self","id"],"arg_types":["agno.vectordb.base.VectorDb","builtins.str"],"fallback":"builtins.function","from_concatenate":false,"implicit":false,"imprecise_arg_kinds":false,"is_bound":false,"is_ellipsis_args":false,"name":"id_exists of VectorDb","ret_type":"builtins.bool","type_guard":null,"type_is":null,"unpack_kwargs":false,"variables":[]}}}},"insert":{".class":"SymbolTableNode","kind":"Mdef","node":{".class":"Decorator","func":{".class":"FuncDef","abstract_status":1,"arg_kinds":[0,0,0,1],"arg_names":["self","content_hash","documents","filters"],"dataclass_transform_spec":null,"deprecated":null,"flags":["is_decorated","is_trivial_body","is_trivial_self"],"fullname":"agno.vectordb.base.VectorDb.insert","name":"insert","original_first_arg":"self","type":{".class":"CallableType","arg_kinds":[0,0,0,1],"arg_names":["self","content_hash","documents","filters"],"arg_types":["agno.vectordb.base.VectorDb","builtins.str",{".class":"Instance","args":["agno.knowledge.document.base.Document"],"extra_attrs":null,"type_ref":"builtins.list"},{".class":"UnionType","items":[{".class":"Instance","args":["builtins.str",{".class":"AnyType","missing_import_name":null,"source_any":null,"type_of_any":2}],"extra_attrs":null,"type_ref":"builtins.dict"},{".class":"NoneType"}],"uses_pep604_syntax":false}],"fallback":"builtins.function","from_concatenate":false,"implicit":false,"imprecise_arg_kinds":false,"is_bound":false,"is_ellipsis_args":false,"name":"insert of VectorDb","ret_type":{".class":"NoneType"},"type_guard":null,"type_is":null,"unpack_kwargs":false,"variables":[]}},"is_overload":false,"var":{".class":"Var","flags":["is_initialized_in_class","is_ready","is_inferred"],"fullname":"agno.vectordb.base.VectorDb.insert","name":"insert","setter_type":null,"type":{".class":"CallableType","arg_kinds":[0,0,0,1],"arg_names":["self","content_hash","documents","filters"],"arg_types":["agno.vectordb.base.VectorDb","builtins.str",{".class":"Instance","args":["agno.knowledge.document.base.Document"],"extra_attrs":null,"type_ref":"builtins.list"},{".class":"UnionType","items":[{".class":"Instance","args":["builtins.str",{".class":"AnyType","missing_import_name":null,"source_any":null,"type_of_any":2}],"extra_attrs":null,"type_ref":"builtins.dict"},{".class":"NoneType"}],"uses_pep604_syntax":false}],"fallback":"builtins.function","from_concatenate":false,"implicit":false,"imprecise_arg_kinds":false,"is_bound":false,"is_ellipsis_args":false,"name":"insert of VectorDb","ret_type":{".class":"NoneType"},"type_guard":null,"type_is":null,"unpack_kwargs":false,"variables":[]}}}},"name":{".class":"SymbolTableNode","implicit":true,"kind":"Mdef","node":{".class":"Var","flags":["is_ready","is_inferred"],"fullname":"agno.vectordb.base.VectorDb.name","name":"name","setter_type":null,"type":"builtins.str"}},"name_exists":{".class":"SymbolTableNode","kind":"Mdef","node":{".class":"Decorator","func":{".class":"FuncDef","abstract_status":1,"arg_kinds":[0,0],"arg_names":["self","name"],"dataclass_transform_spec":null,"deprecated":null,"flags":["is_decorated","is_trivial_body","is_trivial_self"],"fullname":"agno.vectordb.base.VectorDb.name_exists","name":"name_exists","original_first_arg":"self","type":{".class":"CallableType","arg_kinds":[0,0],"arg_names":["self","name"],"arg_types":["agno.vectordb.base.VectorDb","builtins.str"],"fallback":"builtins.function","from_concatenate":false,"implicit":false,"imprecise_arg_kinds":false,"is_bound":false,"is_ellipsis_args":false,"name":"name_exists of VectorDb","ret_type":"builtins.bool","type_guard":null,"type_is":null,"unpack_kwargs":false,"variables":[]}},"is_overload":false,"var":{".class":"Var","flags":["is_initialized_in_class","is_ready","is_inferred"],"fullname":"agno.vectordb.base.VectorDb.name_exists","name":"name_exists","setter_type":null,"type":{".class":"CallableType","arg_kinds":[0,0],"arg_names":["self","name"],"arg_types":["agno.vectordb.base.VectorDb","builtins.str"],"fallback":"builtins.function","from_concatenate":false,"implicit":false,"imprecise_arg_kinds":false,"is_bound":false,"is_ellipsis_args":false,"name":"name_exists of VectorDb","ret_type":"builtins.bool","type_guard":null,"type_is":null,"unpack_kwargs":false,"variables":[]}}}},"optimize":{".class":"SymbolTableNode","kind":"Mdef","node":{".class":"FuncDef","abstract_status":0,"arg_kinds":[0],"arg_names":["self"],"dataclass_transform_spec":null,"deprecated":null,"flags":["is_trivial_self"],"fullname":"agno.vectordb.base.VectorDb.optimize","name":"optimize","original_first_arg":"self","type":{".class":"CallableType","arg_kinds":[0],"arg_names":["self"],"arg_types":["agno.vectordb.base.VectorDb"],"fallback":"builtins.function","from_concatenate":false,"implicit":false,"imprecise_arg_kinds":false,"is_bound":false,"is_ellipsis_args":false,"name":"optimize of VectorDb","ret_type":{".class":"NoneType"},"type_guard":null,"type_is":null,"unpack_kwargs":false,"variables":[]}}},"search":{".class":"SymbolTableNode","kind":"Mdef","node":{".class":"Decorator","func":{".class":"FuncDef","abstract_status":1,"arg_kinds":[0,0,1,1],"arg_names":["self","query","limit","filters"],"dataclass_transform_spec":null,"deprecated":null,"flags":["is_decorated","is_trivial_body","is_trivial_self"],"fullname":"agno.vectordb.base.VectorDb.search","name":"search","original_first_arg":"self","type":{".class":"CallableType","arg_kinds":[0,0,1,1],"arg_names":["self","query","limit","filters"],"arg_types":["agno.vectordb.base.VectorDb","builtins.str","builtins.int",{".class":"UnionType","items":[{".class":"AnyType","missing_import_name":null,"source_any":null,"type_of_any":2},{".class":"NoneType"}],"uses_pep604_syntax":false}],"fallback":"builtins.function","from_concatenate":false,"implicit":false,"imprecise_arg_kinds":false,"is_bound":false,"is_ellipsis_args":false,"name":"search of VectorDb","ret_type":{".class":"Instance","args":["agno.knowledge.document.base.Document"],"extra_attrs":null,"type_ref":"builtins.list"},"type_guard":null,"type_is":null,"unpack_kwargs":false,"variables":[]}},"is_overload":false,"var":{".class":"Var","flags":["is_initialized_in_class","is_ready","is_inferred"],"fullname":"agno.vectordb.base.VectorDb.search","name":"search","setter_type":null,"type":{".class":"CallableType","arg_kinds":[0,0,1,1],"arg_names":["self","query","limit","filters"],"arg_types":["agno.vectordb.base.VectorDb","builtins.str","builtins.int",{".class":"UnionType","items":[{".class":"AnyType","missing_import_name":null,"source_any":null,"type_of_any":2},{".class":"NoneType"}],"uses_pep604_syntax":false}],"fallback":"builtins.function","from_concatenate":false,"implicit":false,"imprecise_arg_kinds":false,"is_bound":false,"is_ellipsis_args":false,"name":"search of VectorDb","ret_type":{".class":"Instance","args":["agno.knowledge.document.base.Document"],"extra_attrs":null,"type_ref":"builtins.list"},"type_guard":null,"type_is":null,"unpack_kwargs":false,"variables":[]}}}},"similarity_threshold":{".class":"SymbolTableNode","implicit":true,"kind":"Mdef","node":{".class":"Var","flags":["is_ready","is_inferred"],"fullname":"agno.vectordb.base.VectorDb.similarity_threshold","name":"similarity_threshold","setter_type":null,"type":{".class":"UnionType","items":["builtins.float",{".class":"NoneType"}],"uses_pep604_syntax":false}}},"update_metadata":{".class":"SymbolTableNode","kind":"Mdef","node":{".class":"FuncDef","abstract_status":0,"arg_kinds":[0,0,0],"arg_names":["self","content_id","metadata"],"dataclass_transform_spec":null,"deprecated":null,"flags":["is_trivial_self"],"fullname":"agno.vectordb.base.VectorDb.update_metadata","name":"update_metadata","original_first_arg":"self","type":{".class":"CallableType","arg_kinds":[0,0,0],"arg_names":["self","content_id","metadata"],"arg_types":["agno.vectordb.base.VectorDb","builtins.str",{".class":"Instance","args":["builtins.str",{".class":"AnyType","missing_import_name":null,"source_any":null,"type_of_any":2}],"extra_attrs":null,"type_ref":"builtins.dict"}],"fallback":"builtins.function","from_concatenate":false,"implicit":false,"imprecise_arg_kinds":false,"is_bound":false,"is_ellipsis_args":false,"name":"update_metadata of VectorDb","ret_type":{".class":"NoneType"},"type_guard":null,"type_is":null,"unpack_kwargs":false,"variables":[]}}},"upsert":{".class":"SymbolTableNode","kind":"Mdef","node":{".class":"Decorator","func":{".class":"FuncDef","abstract_status":1,"arg_kinds":[0,0,0,1],"arg_names":["self","content_hash","documents","filters"],"dataclass_transform_spec":null,"deprecated":null,"flags":["is_decorated","is_trivial_body","is_trivial_self"],"fullname":"agno.vectordb.base.VectorDb.upsert","name":"upsert","original_first_arg":"self","type":{".class":"CallableType","arg_kinds":[0,0,0,1],"arg_names":["self","content_hash","documents","filters"],"arg_types":["agno.vectordb.base.VectorDb","builtins.str",{".class":"Instance","args":["agno.knowledge.document.base.Document"],"extra_attrs":null,"type_ref":"builtins.list"},{".class":"UnionType","items":[{".class":"Instance","args":["builtins.str",{".class":"AnyType","missing_import_name":null,"source_any":null,"type_of_any":2}],"extra_attrs":null,"type_ref":"builtins.dict"},{".class":"NoneType"}],"uses_pep604_syntax":false}],"fallback":"builtins.function","from_concatenate":false,"implicit":false,"imprecise_arg_kinds":false,"is_bound":false,"is_ellipsis_args":false,"name":"upsert of VectorDb","ret_type":{".class":"NoneType"},"type_guard":null,"type_is":null,"unpack_kwargs":false,"variables":[]}},"is_overload":false,"var":{".class":"Var","flags":["is_initialized_in_class","is_ready","is_inferred"],"fullname":"agno.vectordb.base.VectorDb.upsert","name":"upsert","setter_type":null,"type":{".class":"CallableType","arg_kinds":[0,0,0,1],"arg_names":["self","content_hash","documents","filters"],"arg_types":["agno.vectordb.base.VectorDb","builtins.str",{".class":"Instance","args":["agno.knowledge.document.base.Document"],"extra_attrs":null,"type_ref":"builtins.list"},{".class":"UnionType","items":[{".class":"Instance","args":["builtins.str",{".class":"AnyType","missing_import_name":null,"source_any":null,"type_of_any":2}],"extra_attrs":null,"type_ref":"builtins.dict"},{".class":"NoneType"}],"uses_pep604_syntax":false}],"fallback":"builtins.function","from_concatenate":false,"implicit":false,"imprecise_arg_kinds":false,"is_bound":false,"is_ellipsis_args":false,"name":"upsert of VectorDb","ret_type":{".class":"NoneType"},"type_guard":null,"type_is":null,"unpack_kwargs":false,"variables":[]}}}},"upsert_available":{".class":"SymbolTableNode","kind":"Mdef","node":{".class":"FuncDef","abstract_status":0,"arg_kinds":[0],"arg_names":["self"],"dataclass_transform_spec":null,"deprecated":null,"flags":["is_trivial_self"],"fullname":"agno.vectordb.base.VectorDb.upsert_available","name":"upsert_available","original_first_arg":"self","type":{".class":"CallableType","arg_kinds":[0],"arg_names":["self"],"arg_types":["agno.vectordb.base.VectorDb"],"fallback":"builtins.function","from_concatenate":false,"implicit":false,"imprecise_arg_kinds":false,"is_bound":false,"is_ellipsis_args":false,"name":"upsert_available of VectorDb","ret_type":"builtins.bool","type_guard":null,"type_is":null,"unpack_kwargs":false,"variables":[]}}}},"self_type":{".class":"TypeVarType","default":{".class":"AnyType","missing_import_name":null,"source_any":null,"type_of_any":4},"fullname":"agno.vectordb.base.VectorDb.Self","id":0,"name":"Self","namespace":"","upper_bound":"agno.vectordb.base.VectorDb","values":[],"variance":0},"slots":null,"tuple_type":null,"type_vars":[],"typeddict_type":null}},"__annotations__":{".class":"SymbolTableNode","kind":"Gdef","node":{".class":"Var","flags":["is_ready"],"fullname":"agno.vectordb.base.__annotations__","name":"__annotations__","setter_type":null,"type":{".class":"Instance","args":["builtins.str",{".class":"AnyType","missing_import_name":null,"source_any":null,"type_of_any":6}],"extra_attrs":null,"type_ref":"builtins.dict"}}},"__doc__":{".class":"SymbolTableNode","kind":"Gdef","node":{".class":"Var","flags":["is_ready"],"fullname":"agno.vectordb.base.__doc__","name":"__doc__","setter_type":null,"type":"builtins.str"}},"__file__":{".class":"SymbolTableNode","kind":"Gdef","node":{".class":"Var","flags":["is_ready"],"fullname":"agno.vectordb.base.__file__","name":"__file__","setter_type":null,"type":"builtins.str"}},"__name__":{".class":"SymbolTableNode","kind":"Gdef","node":{".class":"Var","flags":["is_ready"],"fullname":"agno.vectordb.base.__name__","name":"__name__","setter_type":null,"type":"builtins.str"}},"__package__":{".class":"SymbolTableNode","kind":"Gdef","node":{".class":"Var","flags":["is_ready"],"fullname":"agno.vectordb.base.__package__","name":"__package__","setter_type":null,"type":"builtins.str"}},"__spec__":{".class":"SymbolTableNode","kind":"Gdef","node":{".class":"Var","flags":["is_ready"],"fullname":"agno.vectordb.base.__spec__","name":"__spec__","setter_type":null,"type":"_frozen_importlib.ModuleSpec"}},"abstractmethod":{".class":"SymbolTableNode","cross_ref":"abc.abstractmethod","kind":"Gdef"},"generate_id":{".class":"SymbolTableNode","cross_ref":"agno.utils.string.generate_id","kind":"Gdef"},"log_warning":{".class":"SymbolTableNode","cross_ref":"agno.utils.log.log_warning","kind":"Gdef"}},"path":"/home/ab916/src/clawbridge/.venv/lib/python3.13/site-packages/agno/vectordb/base.py"}