{".class":"MypyFile","_fullname":"jsonschema_path.paths","future_import_flags":["annotations"],"is_partial_stub_package":false,"is_stub":false,"names":{".class":"SymbolTable","AccessorPath":{".class":"SymbolTableNode","cross_ref":"pathable.paths.AccessorPath","kind":"Gdef"},"Any":{".class":"SymbolTableNode","cross_ref":"typing.Any","kind":"Gdef"},"DRAFT202012":{".class":"SymbolTableNode","cross_ref":"referencing.jsonschema.DRAFT202012","kind":"Gdef"},"FilePathReader":{".class":"SymbolTableNode","cross_ref":"jsonschema_path.readers.FilePathReader","kind":"Gdef"},"FileReader":{".class":"SymbolTableNode","cross_ref":"jsonschema_path.readers.FileReader","kind":"Gdef"},"Iterator":{".class":"SymbolTableNode","cross_ref":"typing.Iterator","kind":"Gdef"},"NOTSET":{".class":"SymbolTableNode","kind":"Gdef","node":{".class":"Var","flags":["is_ready","is_inferred","has_explicit_value"],"fullname":"jsonschema_path.paths.NOTSET","name":"NOTSET","setter_type":null,"type":"builtins.object"}},"Path":{".class":"SymbolTableNode","cross_ref":"pathlib.Path","kind":"Gdef"},"PathReader":{".class":"SymbolTableNode","cross_ref":"jsonschema_path.readers.PathReader","kind":"Gdef"},"Resolved":{".class":"SymbolTableNode","cross_ref":"referencing._core.Resolved","kind":"Gdef"},"ResolverHandlers":{".class":"SymbolTableNode","cross_ref":"jsonschema_path.typing.ResolverHandlers","kind":"Gdef"},"SPEC_SEPARATOR":{".class":"SymbolTableNode","kind":"Gdef","node":{".class":"Var","flags":["is_ready","is_inferred","has_explicit_value"],"fullname":"jsonschema_path.paths.SPEC_SEPARATOR","name":"SPEC_SEPARATOR","setter_type":null,"type":"builtins.str"}},"Schema":{".class":"SymbolTableNode","cross_ref":"jsonschema_path.typing.Schema","kind":"Gdef"},"SchemaAccessor":{".class":"SymbolTableNode","cross_ref":"jsonschema_path.accessors.SchemaAccessor","kind":"Gdef"},"SchemaKey":{".class":"SymbolTableNode","cross_ref":"pathable.types.LookupKey","kind":"Gdef"},"SchemaNode":{".class":"SymbolTableNode","cross_ref":"pathable.types.LookupNode","kind":"Gdef"},"SchemaPath":{".class":"SymbolTableNode","kind":"Gdef","node":{".class":"TypeInfo","_promote":[],"abstract_attributes":[],"alt_promote":null,"bases":[{".class":"Instance","args":[{".class":"TypeAliasType","args":[],"type_ref":"pathable.types.LookupNode"},{".class":"TypeAliasType","args":[],"type_ref":"pathable.types.LookupKey"},{".class":"TypeAliasType","args":[],"type_ref":"pathable.types.LookupValue"}],"extra_attrs":null,"type_ref":"pathable.paths.AccessorPath"}],"dataclass_transform_spec":null,"declared_metaclass":null,"defn":{".class":"ClassDef","fullname":"jsonschema_path.paths.SchemaPath","name":"SchemaPath","type_vars":[]},"deletable_attributes":[],"deprecated":null,"flags":[],"fullname":"jsonschema_path.paths.SchemaPath","has_param_spec_type":false,"metaclass_type":null,"metadata":{},"module_name":"jsonschema_path.paths","mro":["jsonschema_path.paths.SchemaPath","pathable.paths.AccessorPath","pathable.paths.BasePath","builtins.object"],"names":{".class":"SymbolTable","_get_resolved":{".class":"SymbolTableNode","kind":"Mdef","node":{".class":"Decorator","func":{".class":"FuncDef","abstract_status":0,"arg_kinds":[0],"arg_names":["self"],"dataclass_transform_spec":null,"deprecated":null,"flags":["is_property","is_decorated","is_trivial_self"],"fullname":"jsonschema_path.paths.SchemaPath._get_resolved","name":"_get_resolved","original_first_arg":"self","type":{".class":"CallableType","arg_kinds":[0],"arg_names":["self"],"arg_types":["jsonschema_path.paths.SchemaPath"],"fallback":"builtins.function","from_concatenate":false,"implicit":false,"imprecise_arg_kinds":false,"is_bound":false,"is_ellipsis_args":false,"name":"_get_resolved of SchemaPath","ret_type":{".class":"Instance","args":[{".class":"TypeAliasType","args":[],"type_ref":"pathable.types.LookupNode"}],"extra_attrs":null,"type_ref":"referencing._core.Resolved"},"type_guard":null,"type_is":null,"unpack_kwargs":false,"variables":[]}},"is_overload":false,"var":{".class":"Var","flags":["is_initialized_in_class","is_property","is_settable_property","is_ready","is_inferred"],"fullname":"jsonschema_path.paths.SchemaPath._get_resolved","name":"_get_resolved","setter_type":null,"type":{".class":"CallableType","arg_kinds":[0],"arg_names":["self"],"arg_types":["jsonschema_path.paths.SchemaPath"],"fallback":"builtins.function","from_concatenate":false,"implicit":false,"imprecise_arg_kinds":false,"is_bound":false,"is_ellipsis_args":false,"name":"_get_resolved of SchemaPath","ret_type":{".class":"Instance","args":[{".class":"TypeAliasType","args":[],"type_ref":"pathable.types.LookupNode"}],"extra_attrs":null,"type_ref":"referencing._core.Resolved"},"type_guard":null,"type_is":null,"unpack_kwargs":false,"variables":[]}}}},"_parse_args":{".class":"SymbolTableNode","kind":"Mdef","node":{".class":"Decorator","func":{".class":"FuncDef","abstract_status":0,"arg_kinds":[0,0,1],"arg_names":["cls","args","sep"],"dataclass_transform_spec":null,"deprecated":null,"flags":["is_class","is_decorated","is_trivial_self"],"fullname":"jsonschema_path.paths.SchemaPath._parse_args","name":"_parse_args","original_first_arg":"cls","type":{".class":"CallableType","arg_kinds":[0,0,1],"arg_names":["cls","args","sep"],"arg_types":[{".class":"TypeType","is_type_form":false,"item":"jsonschema_path.paths.SchemaPath"},{".class":"Instance","args":[{".class":"AnyType","missing_import_name":null,"source_any":null,"type_of_any":2}],"extra_attrs":null,"type_ref":"typing.Sequence"},"builtins.str"],"fallback":"builtins.function","from_concatenate":false,"implicit":false,"imprecise_arg_kinds":false,"is_bound":false,"is_ellipsis_args":false,"name":"_parse_args of SchemaPath","ret_type":{".class":"Instance","args":[{".class":"TypeAliasType","args":[],"type_ref":"pathable.types.LookupKey"}],"extra_attrs":null,"type_ref":"builtins.tuple"},"type_guard":null,"type_is":null,"unpack_kwargs":false,"variables":[]}},"is_overload":false,"var":{".class":"Var","flags":["is_initialized_in_class","is_classmethod","is_ready","is_inferred"],"fullname":"jsonschema_path.paths.SchemaPath._parse_args","name":"_parse_args","setter_type":null,"type":{".class":"CallableType","arg_kinds":[0,0,1],"arg_names":["cls","args","sep"],"arg_types":[{".class":"TypeType","is_type_form":false,"item":"jsonschema_path.paths.SchemaPath"},{".class":"Instance","args":[{".class":"AnyType","missing_import_name":null,"source_any":null,"type_of_any":2}],"extra_attrs":null,"type_ref":"typing.Sequence"},"builtins.str"],"fallback":"builtins.function","from_concatenate":false,"implicit":false,"imprecise_arg_kinds":false,"is_bound":false,"is_ellipsis_args":false,"name":"_parse_args of SchemaPath","ret_type":{".class":"Instance","args":[{".class":"TypeAliasType","args":[],"type_ref":"pathable.types.LookupKey"}],"extra_attrs":null,"type_ref":"builtins.tuple"},"type_guard":null,"type_is":null,"unpack_kwargs":false,"variables":[]}}}},"as_uri":{".class":"SymbolTableNode","kind":"Mdef","node":{".class":"FuncDef","abstract_status":0,"arg_kinds":[0],"arg_names":["self"],"dataclass_transform_spec":null,"deprecated":null,"flags":["is_trivial_self"],"fullname":"jsonschema_path.paths.SchemaPath.as_uri","name":"as_uri","original_first_arg":"self","type":{".class":"CallableType","arg_kinds":[0],"arg_names":["self"],"arg_types":["jsonschema_path.paths.SchemaPath"],"fallback":"builtins.function","from_concatenate":false,"implicit":false,"imprecise_arg_kinds":false,"is_bound":false,"is_ellipsis_args":false,"name":"as_uri of SchemaPath","ret_type":"builtins.str","type_guard":null,"type_is":null,"unpack_kwargs":false,"variables":[]}}},"base_uri":{".class":"SymbolTableNode","kind":"Mdef","node":{".class":"Decorator","func":{".class":"FuncDef","abstract_status":0,"arg_kinds":[0],"arg_names":["self"],"dataclass_transform_spec":null,"deprecated":null,"flags":["is_property","is_decorated","is_trivial_self"],"fullname":"jsonschema_path.paths.SchemaPath.base_uri","name":"base_uri","original_first_arg":"self","type":{".class":"CallableType","arg_kinds":[0],"arg_names":["self"],"arg_types":["jsonschema_path.paths.SchemaPath"],"fallback":"builtins.function","from_concatenate":false,"implicit":false,"imprecise_arg_kinds":false,"is_bound":false,"is_ellipsis_args":false,"name":"base_uri of SchemaPath","ret_type":"builtins.str","type_guard":null,"type_is":null,"unpack_kwargs":false,"variables":[]}},"is_overload":false,"var":{".class":"Var","flags":["is_initialized_in_class","is_property","is_ready","is_inferred"],"fullname":"jsonschema_path.paths.SchemaPath.base_uri","name":"base_uri","setter_type":null,"type":{".class":"CallableType","arg_kinds":[0],"arg_names":["self"],"arg_types":["jsonschema_path.paths.SchemaPath"],"fallback":"builtins.function","from_concatenate":false,"implicit":false,"imprecise_arg_kinds":false,"is_bound":false,"is_ellipsis_args":false,"name":"base_uri of SchemaPath","ret_type":"builtins.str","type_guard":null,"type_is":null,"unpack_kwargs":false,"variables":[]}}}},"from_dict":{".class":"SymbolTableNode","kind":"Mdef","node":{".class":"Decorator","func":{".class":"FuncDef","abstract_status":0,"arg_kinds":[0,0,2,5,5,5,5,5,5,5],"arg_names":["cls","data","args","separator","specification","base_uri","handlers","resolved_cache_maxsize","spec_url","ref_resolver_handlers"],"dataclass_transform_spec":null,"deprecated":null,"flags":["is_class","is_decorated"],"fullname":"jsonschema_path.paths.SchemaPath.from_dict","name":"from_dict","original_first_arg":"cls","type":{".class":"CallableType","arg_kinds":[0,0,2,5,5,5,5,5,5,5],"arg_names":["cls","data","args","separator","specification","base_uri","handlers","resolved_cache_maxsize","spec_url","ref_resolver_handlers"],"arg_types":[{".class":"TypeType","is_type_form":false,"item":{".class":"TypeVarType","default":{".class":"AnyType","missing_import_name":null,"source_any":null,"type_of_any":4},"fullname":"jsonschema_path.paths.TSchemaPath","id":-1,"name":"TSchemaPath","namespace":"jsonschema_path.paths.SchemaPath.from_dict","upper_bound":"jsonschema_path.paths.SchemaPath","values":[],"variance":0}},{".class":"TypeAliasType","args":[],"type_ref":"jsonschema_path.typing.Schema"},{".class":"AnyType","missing_import_name":null,"source_any":null,"type_of_any":2},"builtins.str",{".class":"Instance","args":[{".class":"TypeAliasType","args":[],"type_ref":"jsonschema_path.typing.Schema"}],"extra_attrs":null,"type_ref":"referencing._core.Specification"},"builtins.str",{".class":"TypeAliasType","args":[],"type_ref":"jsonschema_path.typing.ResolverHandlers"},"builtins.int",{".class":"UnionType","items":["builtins.str",{".class":"NoneType"}],"uses_pep604_syntax":true},{".class":"UnionType","items":[{".class":"TypeAliasType","args":[],"type_ref":"jsonschema_path.typing.ResolverHandlers"},{".class":"NoneType"}],"uses_pep604_syntax":true}],"fallback":"builtins.function","from_concatenate":false,"implicit":false,"imprecise_arg_kinds":false,"is_bound":false,"is_ellipsis_args":false,"name":"from_dict of SchemaPath","ret_type":{".class":"TypeVarType","default":{".class":"AnyType","missing_import_name":null,"source_any":null,"type_of_any":4},"fullname":"jsonschema_path.paths.TSchemaPath","id":-1,"name":"TSchemaPath","namespace":"jsonschema_path.paths.SchemaPath.from_dict","upper_bound":"jsonschema_path.paths.SchemaPath","values":[],"variance":0},"type_guard":null,"type_is":null,"unpack_kwargs":false,"variables":[{".class":"TypeVarType","default":{".class":"AnyType","missing_import_name":null,"source_any":null,"type_of_any":4},"fullname":"jsonschema_path.paths.TSchemaPath","id":-1,"name":"TSchemaPath","namespace":"jsonschema_path.paths.SchemaPath.from_dict","upper_bound":"jsonschema_path.paths.SchemaPath","values":[],"variance":0}]}},"is_overload":false,"var":{".class":"Var","flags":["is_initialized_in_class","is_classmethod","is_ready","is_inferred"],"fullname":"jsonschema_path.paths.SchemaPath.from_dict","name":"from_dict","setter_type":null,"type":{".class":"CallableType","arg_kinds":[0,0,2,5,5,5,5,5,5,5],"arg_names":["cls","data","args","separator","specification","base_uri","handlers","resolved_cache_maxsize","spec_url","ref_resolver_handlers"],"arg_types":[{".class":"TypeType","is_type_form":false,"item":{".class":"TypeVarType","default":{".class":"AnyType","missing_import_name":null,"source_any":null,"type_of_any":4},"fullname":"jsonschema_path.paths.TSchemaPath","id":-1,"name":"TSchemaPath","namespace":"jsonschema_path.paths.SchemaPath.from_dict","upper_bound":"jsonschema_path.paths.SchemaPath","values":[],"variance":0}},{".class":"TypeAliasType","args":[],"type_ref":"jsonschema_path.typing.Schema"},{".class":"AnyType","missing_import_name":null,"source_any":null,"type_of_any":2},"builtins.str",{".class":"Instance","args":[{".class":"TypeAliasType","args":[],"type_ref":"jsonschema_path.typing.Schema"}],"extra_attrs":null,"type_ref":"referencing._core.Specification"},"builtins.str",{".class":"TypeAliasType","args":[],"type_ref":"jsonschema_path.typing.ResolverHandlers"},"builtins.int",{".class":"UnionType","items":["builtins.str",{".class":"NoneType"}],"uses_pep604_syntax":true},{".class":"UnionType","items":[{".class":"TypeAliasType","args":[],"type_ref":"jsonschema_path.typing.ResolverHandlers"},{".class":"NoneType"}],"uses_pep604_syntax":true}],"fallback":"builtins.function","from_concatenate":false,"implicit":false,"imprecise_arg_kinds":false,"is_bound":false,"is_ellipsis_args":false,"name":"from_dict of SchemaPath","ret_type":{".class":"TypeVarType","default":{".class":"AnyType","missing_import_name":null,"source_any":null,"type_of_any":4},"fullname":"jsonschema_path.paths.TSchemaPath","id":-1,"name":"TSchemaPath","namespace":"jsonschema_path.paths.SchemaPath.from_dict","upper_bound":"jsonschema_path.paths.SchemaPath","values":[],"variance":0},"type_guard":null,"type_is":null,"unpack_kwargs":false,"variables":[{".class":"TypeVarType","default":{".class":"AnyType","missing_import_name":null,"source_any":null,"type_of_any":4},"fullname":"jsonschema_path.paths.TSchemaPath","id":-1,"name":"TSchemaPath","namespace":"jsonschema_path.paths.SchemaPath.from_dict","upper_bound":"jsonschema_path.paths.SchemaPath","values":[],"variance":0}]}}}},"from_file":{".class":"SymbolTableNode","kind":"Mdef","node":{".class":"Decorator","func":{".class":"FuncDef","abstract_status":0,"arg_kinds":[0,0,1,1,1],"arg_names":["cls","fileobj","base_uri","spec_url","resolved_cache_maxsize"],"dataclass_transform_spec":null,"deprecated":null,"flags":["is_class","is_decorated"],"fullname":"jsonschema_path.paths.SchemaPath.from_file","name":"from_file","original_first_arg":"cls","type":{".class":"CallableType","arg_kinds":[0,0,1,1,1],"arg_names":["cls","fileobj","base_uri","spec_url","resolved_cache_maxsize"],"arg_types":[{".class":"TypeType","is_type_form":false,"item":{".class":"TypeVarType","default":{".class":"AnyType","missing_import_name":null,"source_any":null,"type_of_any":4},"fullname":"jsonschema_path.paths.TSchemaPath","id":-1,"name":"TSchemaPath","namespace":"jsonschema_path.paths.SchemaPath.from_file","upper_bound":"jsonschema_path.paths.SchemaPath","values":[],"variance":0}},"jsonschema_path.handlers.protocols.SupportsRead","builtins.str",{".class":"UnionType","items":["builtins.str",{".class":"NoneType"}],"uses_pep604_syntax":true},"builtins.int"],"fallback":"builtins.function","from_concatenate":false,"implicit":false,"imprecise_arg_kinds":false,"is_bound":false,"is_ellipsis_args":false,"name":"from_file of SchemaPath","ret_type":{".class":"TypeVarType","default":{".class":"AnyType","missing_import_name":null,"source_any":null,"type_of_any":4},"fullname":"jsonschema_path.paths.TSchemaPath","id":-1,"name":"TSchemaPath","namespace":"jsonschema_path.paths.SchemaPath.from_file","upper_bound":"jsonschema_path.paths.SchemaPath","values":[],"variance":0},"type_guard":null,"type_is":null,"unpack_kwargs":false,"variables":[{".class":"TypeVarType","default":{".class":"AnyType","missing_import_name":null,"source_any":null,"type_of_any":4},"fullname":"jsonschema_path.paths.TSchemaPath","id":-1,"name":"TSchemaPath","namespace":"jsonschema_path.paths.SchemaPath.from_file","upper_bound":"jsonschema_path.paths.SchemaPath","values":[],"variance":0}]}},"is_overload":false,"var":{".class":"Var","flags":["is_initialized_in_class","is_classmethod","is_ready","is_inferred"],"fullname":"jsonschema_path.paths.SchemaPath.from_file","name":"from_file","setter_type":null,"type":{".class":"CallableType","arg_kinds":[0,0,1,1,1],"arg_names":["cls","fileobj","base_uri","spec_url","resolved_cache_maxsize"],"arg_types":[{".class":"TypeType","is_type_form":false,"item":{".class":"TypeVarType","default":{".class":"AnyType","missing_import_name":null,"source_any":null,"type_of_any":4},"fullname":"jsonschema_path.paths.TSchemaPath","id":-1,"name":"TSchemaPath","namespace":"jsonschema_path.paths.SchemaPath.from_file","upper_bound":"jsonschema_path.paths.SchemaPath","values":[],"variance":0}},"jsonschema_path.handlers.protocols.SupportsRead","builtins.str",{".class":"UnionType","items":["builtins.str",{".class":"NoneType"}],"uses_pep604_syntax":true},"builtins.int"],"fallback":"builtins.function","from_concatenate":false,"implicit":false,"imprecise_arg_kinds":false,"is_bound":false,"is_ellipsis_args":false,"name":"from_file of SchemaPath","ret_type":{".class":"TypeVarType","default":{".class":"AnyType","missing_import_name":null,"source_any":null,"type_of_any":4},"fullname":"jsonschema_path.paths.TSchemaPath","id":-1,"name":"TSchemaPath","namespace":"jsonschema_path.paths.SchemaPath.from_file","upper_bound":"jsonschema_path.paths.SchemaPath","values":[],"variance":0},"type_guard":null,"type_is":null,"unpack_kwargs":false,"variables":[{".class":"TypeVarType","default":{".class":"AnyType","missing_import_name":null,"source_any":null,"type_of_any":4},"fullname":"jsonschema_path.paths.TSchemaPath","id":-1,"name":"TSchemaPath","namespace":"jsonschema_path.paths.SchemaPath.from_file","upper_bound":"jsonschema_path.paths.SchemaPath","values":[],"variance":0}]}}}},"from_file_path":{".class":"SymbolTableNode","kind":"Mdef","node":{".class":"Decorator","func":{".class":"FuncDef","abstract_status":0,"arg_kinds":[0,0,1],"arg_names":["cls","file_path","resolved_cache_maxsize"],"dataclass_transform_spec":null,"deprecated":null,"flags":["is_class","is_decorated"],"fullname":"jsonschema_path.paths.SchemaPath.from_file_path","name":"from_file_path","original_first_arg":"cls","type":{".class":"CallableType","arg_kinds":[0,0,1],"arg_names":["cls","file_path","resolved_cache_maxsize"],"arg_types":[{".class":"TypeType","is_type_form":false,"item":{".class":"TypeVarType","default":{".class":"AnyType","missing_import_name":null,"source_any":null,"type_of_any":4},"fullname":"jsonschema_path.paths.TSchemaPath","id":-1,"name":"TSchemaPath","namespace":"jsonschema_path.paths.SchemaPath.from_file_path","upper_bound":"jsonschema_path.paths.SchemaPath","values":[],"variance":0}},"builtins.str","builtins.int"],"fallback":"builtins.function","from_concatenate":false,"implicit":false,"imprecise_arg_kinds":false,"is_bound":false,"is_ellipsis_args":false,"name":"from_file_path of SchemaPath","ret_type":{".class":"TypeVarType","default":{".class":"AnyType","missing_import_name":null,"source_any":null,"type_of_any":4},"fullname":"jsonschema_path.paths.TSchemaPath","id":-1,"name":"TSchemaPath","namespace":"jsonschema_path.paths.SchemaPath.from_file_path","upper_bound":"jsonschema_path.paths.SchemaPath","values":[],"variance":0},"type_guard":null,"type_is":null,"unpack_kwargs":false,"variables":[{".class":"TypeVarType","default":{".class":"AnyType","missing_import_name":null,"source_any":null,"type_of_any":4},"fullname":"jsonschema_path.paths.TSchemaPath","id":-1,"name":"TSchemaPath","namespace":"jsonschema_path.paths.SchemaPath.from_file_path","upper_bound":"jsonschema_path.paths.SchemaPath","values":[],"variance":0}]}},"is_overload":false,"var":{".class":"Var","flags":["is_initialized_in_class","is_classmethod","is_ready","is_inferred"],"fullname":"jsonschema_path.paths.SchemaPath.from_file_path","name":"from_file_path","setter_type":null,"type":{".class":"CallableType","arg_kinds":[0,0,1],"arg_names":["cls","file_path","resolved_cache_maxsize"],"arg_types":[{".class":"TypeType","is_type_form":false,"item":{".class":"TypeVarType","default":{".class":"AnyType","missing_import_name":null,"source_any":null,"type_of_any":4},"fullname":"jsonschema_path.paths.TSchemaPath","id":-1,"name":"TSchemaPath","namespace":"jsonschema_path.paths.SchemaPath.from_file_path","upper_bound":"jsonschema_path.paths.SchemaPath","values":[],"variance":0}},"builtins.str","builtins.int"],"fallback":"builtins.function","from_concatenate":false,"implicit":false,"imprecise_arg_kinds":false,"is_bound":false,"is_ellipsis_args":false,"name":"from_file_path of SchemaPath","ret_type":{".class":"TypeVarType","default":{".class":"AnyType","missing_import_name":null,"source_any":null,"type_of_any":4},"fullname":"jsonschema_path.paths.TSchemaPath","id":-1,"name":"TSchemaPath","namespace":"jsonschema_path.paths.SchemaPath.from_file_path","upper_bound":"jsonschema_path.paths.SchemaPath","values":[],"variance":0},"type_guard":null,"type_is":null,"unpack_kwargs":false,"variables":[{".class":"TypeVarType","default":{".class":"AnyType","missing_import_name":null,"source_any":null,"type_of_any":4},"fullname":"jsonschema_path.paths.TSchemaPath","id":-1,"name":"TSchemaPath","namespace":"jsonschema_path.paths.SchemaPath.from_file_path","upper_bound":"jsonschema_path.paths.SchemaPath","values":[],"variance":0}]}}}},"from_path":{".class":"SymbolTableNode","kind":"Mdef","node":{".class":"Decorator","func":{".class":"FuncDef","abstract_status":0,"arg_kinds":[0,0,1],"arg_names":["cls","path","resolved_cache_maxsize"],"dataclass_transform_spec":null,"deprecated":null,"flags":["is_class","is_decorated"],"fullname":"jsonschema_path.paths.SchemaPath.from_path","name":"from_path","original_first_arg":"cls","type":{".class":"CallableType","arg_kinds":[0,0,1],"arg_names":["cls","path","resolved_cache_maxsize"],"arg_types":[{".class":"TypeType","is_type_form":false,"item":{".class":"TypeVarType","default":{".class":"AnyType","missing_import_name":null,"source_any":null,"type_of_any":4},"fullname":"jsonschema_path.paths.TSchemaPath","id":-1,"name":"TSchemaPath","namespace":"jsonschema_path.paths.SchemaPath.from_path","upper_bound":"jsonschema_path.paths.SchemaPath","values":[],"variance":0}},"pathlib.Path","builtins.int"],"fallback":"builtins.function","from_concatenate":false,"implicit":false,"imprecise_arg_kinds":false,"is_bound":false,"is_ellipsis_args":false,"name":"from_path of SchemaPath","ret_type":{".class":"TypeVarType","default":{".class":"AnyType","missing_import_name":null,"source_any":null,"type_of_any":4},"fullname":"jsonschema_path.paths.TSchemaPath","id":-1,"name":"TSchemaPath","namespace":"jsonschema_path.paths.SchemaPath.from_path","upper_bound":"jsonschema_path.paths.SchemaPath","values":[],"variance":0},"type_guard":null,"type_is":null,"unpack_kwargs":false,"variables":[{".class":"TypeVarType","default":{".class":"AnyType","missing_import_name":null,"source_any":null,"type_of_any":4},"fullname":"jsonschema_path.paths.TSchemaPath","id":-1,"name":"TSchemaPath","namespace":"jsonschema_path.paths.SchemaPath.from_path","upper_bound":"jsonschema_path.paths.SchemaPath","values":[],"variance":0}]}},"is_overload":false,"var":{".class":"Var","flags":["is_initialized_in_class","is_classmethod","is_ready","is_inferred"],"fullname":"jsonschema_path.paths.SchemaPath.from_path","name":"from_path","setter_type":null,"type":{".class":"CallableType","arg_kinds":[0,0,1],"arg_names":["cls","path","resolved_cache_maxsize"],"arg_types":[{".class":"TypeType","is_type_form":false,"item":{".class":"TypeVarType","default":{".class":"AnyType","missing_import_name":null,"source_any":null,"type_of_any":4},"fullname":"jsonschema_path.paths.TSchemaPath","id":-1,"name":"TSchemaPath","namespace":"jsonschema_path.paths.SchemaPath.from_path","upper_bound":"jsonschema_path.paths.SchemaPath","values":[],"variance":0}},"pathlib.Path","builtins.int"],"fallback":"builtins.function","from_concatenate":false,"implicit":false,"imprecise_arg_kinds":false,"is_bound":false,"is_ellipsis_args":false,"name":"from_path of SchemaPath","ret_type":{".class":"TypeVarType","default":{".class":"AnyType","missing_import_name":null,"source_any":null,"type_of_any":4},"fullname":"jsonschema_path.paths.TSchemaPath","id":-1,"name":"TSchemaPath","namespace":"jsonschema_path.paths.SchemaPath.from_path","upper_bound":"jsonschema_path.paths.SchemaPath","values":[],"variance":0},"type_guard":null,"type_is":null,"unpack_kwargs":false,"variables":[{".class":"TypeVarType","default":{".class":"AnyType","missing_import_name":null,"source_any":null,"type_of_any":4},"fullname":"jsonschema_path.paths.TSchemaPath","id":-1,"name":"TSchemaPath","namespace":"jsonschema_path.paths.SchemaPath.from_path","upper_bound":"jsonschema_path.paths.SchemaPath","values":[],"variance":0}]}}}},"open":{".class":"SymbolTableNode","kind":"Mdef","node":{".class":"Decorator","func":{".class":"FuncDef","abstract_status":0,"arg_kinds":[0],"arg_names":["self"],"dataclass_transform_spec":null,"deprecated":null,"flags":["is_decorated","is_trivial_self"],"fullname":"jsonschema_path.paths.SchemaPath.open","name":"open","original_first_arg":"self","type":{".class":"CallableType","arg_kinds":[0],"arg_names":["self"],"arg_types":["jsonschema_path.paths.SchemaPath"],"fallback":"builtins.function","from_concatenate":false,"implicit":false,"imprecise_arg_kinds":false,"is_bound":false,"is_ellipsis_args":false,"name":"open of SchemaPath","ret_type":{".class":"AnyType","missing_import_name":null,"source_any":null,"type_of_any":2},"type_guard":null,"type_is":null,"unpack_kwargs":false,"variables":[]}},"is_overload":false,"var":{".class":"Var","flags":["is_initialized_in_class","is_ready","is_inferred"],"fullname":"jsonschema_path.paths.SchemaPath.open","name":"open","setter_type":null,"type":{".class":"CallableType","arg_kinds":[0],"arg_names":["self"],"arg_types":["jsonschema_path.paths.SchemaPath"],"fallback":"builtins.function","from_concatenate":false,"implicit":false,"imprecise_arg_kinds":false,"is_bound":false,"is_ellipsis_args":false,"name":"open of SchemaPath","ret_type":{".class":"Instance","args":[{".class":"AnyType","missing_import_name":null,"source_any":{".class":"AnyType","missing_import_name":null,"source_any":null,"type_of_any":2},"type_of_any":7},{".class":"NoneType"},{".class":"NoneType"}],"extra_attrs":null,"type_ref":"contextlib._GeneratorContextManager"},"type_guard":null,"type_is":null,"unpack_kwargs":false,"variables":[]}}}},"read_bool":{".class":"SymbolTableNode","kind":"Mdef","node":{".class":"OverloadedFuncDef","deprecated":null,"flags":[],"fullname":"jsonschema_path.paths.SchemaPath.read_bool","impl":{".class":"FuncDef","abstract_status":0,"arg_kinds":[0,1],"arg_names":["self","default"],"dataclass_transform_spec":null,"deprecated":null,"flags":["is_overload","is_trivial_self"],"fullname":"jsonschema_path.paths.SchemaPath.read_bool","name":"read_bool","original_first_arg":"self","type":{".class":"CallableType","arg_kinds":[0,1],"arg_names":["self","default"],"arg_types":["jsonschema_path.paths.SchemaPath","builtins.object"],"fallback":"builtins.function","from_concatenate":false,"implicit":false,"imprecise_arg_kinds":false,"is_bound":false,"is_ellipsis_args":false,"name":"read_bool of SchemaPath","ret_type":"builtins.object","type_guard":null,"type_is":null,"unpack_kwargs":false,"variables":[]}},"items":[{".class":"Decorator","func":{".class":"FuncDef","abstract_status":0,"arg_kinds":[0],"arg_names":["self"],"dataclass_transform_spec":null,"deprecated":null,"flags":["is_overload","is_decorated","is_trivial_self"],"fullname":"jsonschema_path.paths.SchemaPath.read_bool","name":"read_bool","original_first_arg":"self","type":{".class":"CallableType","arg_kinds":[0],"arg_names":["self"],"arg_types":["jsonschema_path.paths.SchemaPath"],"fallback":"builtins.function","from_concatenate":false,"implicit":false,"imprecise_arg_kinds":false,"is_bound":false,"is_ellipsis_args":false,"name":"read_bool of SchemaPath","ret_type":"builtins.bool","type_guard":null,"type_is":null,"unpack_kwargs":false,"variables":[]}},"is_overload":true,"var":{".class":"Var","flags":["is_ready","is_inferred"],"fullname":"jsonschema_path.paths.SchemaPath.read_bool","name":"read_bool","setter_type":null,"type":{".class":"CallableType","arg_kinds":[0],"arg_names":["self"],"arg_types":["jsonschema_path.paths.SchemaPath"],"fallback":"builtins.function","from_concatenate":false,"implicit":false,"imprecise_arg_kinds":false,"is_bound":false,"is_ellipsis_args":false,"name":"read_bool of SchemaPath","ret_type":"builtins.bool","type_guard":null,"type_is":null,"unpack_kwargs":false,"variables":[]}}},{".class":"Decorator","func":{".class":"FuncDef","abstract_status":0,"arg_kinds":[0,0],"arg_names":["self","default"],"dataclass_transform_spec":null,"deprecated":null,"flags":["is_overload","is_decorated","is_trivial_self"],"fullname":"jsonschema_path.paths.SchemaPath.read_bool","name":"read_bool","original_first_arg":"self","type":{".class":"CallableType","arg_kinds":[0,0],"arg_names":["self","default"],"arg_types":["jsonschema_path.paths.SchemaPath",{".class":"TypeVarType","default":{".class":"AnyType","missing_import_name":null,"source_any":null,"type_of_any":4},"fullname":"jsonschema_path.paths.TDefault","id":-1,"name":"TDefault","namespace":"jsonschema_path.paths.SchemaPath.read_bool#1","upper_bound":"builtins.object","values":[],"variance":0}],"fallback":"builtins.function","from_concatenate":false,"implicit":false,"imprecise_arg_kinds":false,"is_bound":false,"is_ellipsis_args":false,"name":"read_bool of SchemaPath","ret_type":{".class":"UnionType","items":["builtins.bool",{".class":"TypeVarType","default":{".class":"AnyType","missing_import_name":null,"source_any":null,"type_of_any":4},"fullname":"jsonschema_path.paths.TDefault","id":-1,"name":"TDefault","namespace":"jsonschema_path.paths.SchemaPath.read_bool#1","upper_bound":"builtins.object","values":[],"variance":0}],"uses_pep604_syntax":true},"type_guard":null,"type_is":null,"unpack_kwargs":false,"variables":[{".class":"TypeVarType","default":{".class":"AnyType","missing_import_name":null,"source_any":null,"type_of_any":4},"fullname":"jsonschema_path.paths.TDefault","id":-1,"name":"TDefault","namespace":"jsonschema_path.paths.SchemaPath.read_bool#1","upper_bound":"builtins.object","values":[],"variance":0}]}},"is_overload":true,"var":{".class":"Var","flags":["is_ready","is_inferred"],"fullname":"jsonschema_path.paths.SchemaPath.read_bool","name":"read_bool","setter_type":null,"type":{".class":"CallableType","arg_kinds":[0,0],"arg_names":["self","default"],"arg_types":["jsonschema_path.paths.SchemaPath",{".class":"TypeVarType","default":{".class":"AnyType","missing_import_name":null,"source_any":null,"type_of_any":4},"fullname":"jsonschema_path.paths.TDefault","id":-1,"name":"TDefault","namespace":"jsonschema_path.paths.SchemaPath.read_bool#1","upper_bound":"builtins.object","values":[],"variance":0}],"fallback":"builtins.function","from_concatenate":false,"implicit":false,"imprecise_arg_kinds":false,"is_bound":false,"is_ellipsis_args":false,"name":"read_bool of SchemaPath","ret_type":{".class":"UnionType","items":["builtins.bool",{".class":"TypeVarType","default":{".class":"AnyType","missing_import_name":null,"source_any":null,"type_of_any":4},"fullname":"jsonschema_path.paths.TDefault","id":-1,"name":"TDefault","namespace":"jsonschema_path.paths.SchemaPath.read_bool#1","upper_bound":"builtins.object","values":[],"variance":0}],"uses_pep604_syntax":true},"type_guard":null,"type_is":null,"unpack_kwargs":false,"variables":[{".class":"TypeVarType","default":{".class":"AnyType","missing_import_name":null,"source_any":null,"type_of_any":4},"fullname":"jsonschema_path.paths.TDefault","id":-1,"name":"TDefault","namespace":"jsonschema_path.paths.SchemaPath.read_bool#1","upper_bound":"builtins.object","values":[],"variance":0}]}}}],"setter_index":null,"type":{".class":"Overloaded","items":[{".class":"CallableType","arg_kinds":[0],"arg_names":["self"],"arg_types":["jsonschema_path.paths.SchemaPath"],"fallback":"builtins.function","from_concatenate":false,"implicit":false,"imprecise_arg_kinds":false,"is_bound":false,"is_ellipsis_args":false,"name":"read_bool of SchemaPath","ret_type":"builtins.bool","type_guard":null,"type_is":null,"unpack_kwargs":false,"variables":[]},{".class":"CallableType","arg_kinds":[0,0],"arg_names":["self","default"],"arg_types":["jsonschema_path.paths.SchemaPath",{".class":"TypeVarType","default":{".class":"AnyType","missing_import_name":null,"source_any":null,"type_of_any":4},"fullname":"jsonschema_path.paths.TDefault","id":-1,"name":"TDefault","namespace":"jsonschema_path.paths.SchemaPath.read_bool#1","upper_bound":"builtins.object","values":[],"variance":0}],"fallback":"builtins.function","from_concatenate":false,"implicit":false,"imprecise_arg_kinds":false,"is_bound":false,"is_ellipsis_args":false,"name":"read_bool of SchemaPath","ret_type":{".class":"UnionType","items":["builtins.bool",{".class":"TypeVarType","default":{".class":"AnyType","missing_import_name":null,"source_any":null,"type_of_any":4},"fullname":"jsonschema_path.paths.TDefault","id":-1,"name":"TDefault","namespace":"jsonschema_path.paths.SchemaPath.read_bool#1","upper_bound":"builtins.object","values":[],"variance":0}],"uses_pep604_syntax":true},"type_guard":null,"type_is":null,"unpack_kwargs":false,"variables":[{".class":"TypeVarType","default":{".class":"AnyType","missing_import_name":null,"source_any":null,"type_of_any":4},"fullname":"jsonschema_path.paths.TDefault","id":-1,"name":"TDefault","namespace":"jsonschema_path.paths.SchemaPath.read_bool#1","upper_bound":"builtins.object","values":[],"variance":0}]}]}}},"read_str":{".class":"SymbolTableNode","kind":"Mdef","node":{".class":"OverloadedFuncDef","deprecated":null,"flags":[],"fullname":"jsonschema_path.paths.SchemaPath.read_str","impl":{".class":"FuncDef","abstract_status":0,"arg_kinds":[0,1],"arg_names":["self","default"],"dataclass_transform_spec":null,"deprecated":null,"flags":["is_overload","is_trivial_self"],"fullname":"jsonschema_path.paths.SchemaPath.read_str","name":"read_str","original_first_arg":"self","type":{".class":"CallableType","arg_kinds":[0,1],"arg_names":["self","default"],"arg_types":["jsonschema_path.paths.SchemaPath","builtins.object"],"fallback":"builtins.function","from_concatenate":false,"implicit":false,"imprecise_arg_kinds":false,"is_bound":false,"is_ellipsis_args":false,"name":"read_str of SchemaPath","ret_type":"builtins.object","type_guard":null,"type_is":null,"unpack_kwargs":false,"variables":[]}},"items":[{".class":"Decorator","func":{".class":"FuncDef","abstract_status":0,"arg_kinds":[0],"arg_names":["self"],"dataclass_transform_spec":null,"deprecated":null,"flags":["is_overload","is_decorated","is_trivial_self"],"fullname":"jsonschema_path.paths.SchemaPath.read_str","name":"read_str","original_first_arg":"self","type":{".class":"CallableType","arg_kinds":[0],"arg_names":["self"],"arg_types":["jsonschema_path.paths.SchemaPath"],"fallback":"builtins.function","from_concatenate":false,"implicit":false,"imprecise_arg_kinds":false,"is_bound":false,"is_ellipsis_args":false,"name":"read_str of SchemaPath","ret_type":"builtins.str","type_guard":null,"type_is":null,"unpack_kwargs":false,"variables":[]}},"is_overload":true,"var":{".class":"Var","flags":["is_ready","is_inferred"],"fullname":"jsonschema_path.paths.SchemaPath.read_str","name":"read_str","setter_type":null,"type":{".class":"CallableType","arg_kinds":[0],"arg_names":["self"],"arg_types":["jsonschema_path.paths.SchemaPath"],"fallback":"builtins.function","from_concatenate":false,"implicit":false,"imprecise_arg_kinds":false,"is_bound":false,"is_ellipsis_args":false,"name":"read_str of SchemaPath","ret_type":"builtins.str","type_guard":null,"type_is":null,"unpack_kwargs":false,"variables":[]}}},{".class":"Decorator","func":{".class":"FuncDef","abstract_status":0,"arg_kinds":[0,0],"arg_names":["self","default"],"dataclass_transform_spec":null,"deprecated":null,"flags":["is_overload","is_decorated","is_trivial_self"],"fullname":"jsonschema_path.paths.SchemaPath.read_str","name":"read_str","original_first_arg":"self","type":{".class":"CallableType","arg_kinds":[0,0],"arg_names":["self","default"],"arg_types":["jsonschema_path.paths.SchemaPath",{".class":"TypeVarType","default":{".class":"AnyType","missing_import_name":null,"source_any":null,"type_of_any":4},"fullname":"jsonschema_path.paths.TDefault","id":-1,"name":"TDefault","namespace":"jsonschema_path.paths.SchemaPath.read_str#1","upper_bound":"builtins.object","values":[],"variance":0}],"fallback":"builtins.function","from_concatenate":false,"implicit":false,"imprecise_arg_kinds":false,"is_bound":false,"is_ellipsis_args":false,"name":"read_str of SchemaPath","ret_type":{".class":"UnionType","items":["builtins.str",{".class":"TypeVarType","default":{".class":"AnyType","missing_import_name":null,"source_any":null,"type_of_any":4},"fullname":"jsonschema_path.paths.TDefault","id":-1,"name":"TDefault","namespace":"jsonschema_path.paths.SchemaPath.read_str#1","upper_bound":"builtins.object","values":[],"variance":0}],"uses_pep604_syntax":true},"type_guard":null,"type_is":null,"unpack_kwargs":false,"variables":[{".class":"TypeVarType","default":{".class":"AnyType","missing_import_name":null,"source_any":null,"type_of_any":4},"fullname":"jsonschema_path.paths.TDefault","id":-1,"name":"TDefault","namespace":"jsonschema_path.paths.SchemaPath.read_str#1","upper_bound":"builtins.object","values":[],"variance":0}]}},"is_overload":true,"var":{".class":"Var","flags":["is_ready","is_inferred"],"fullname":"jsonschema_path.paths.SchemaPath.read_str","name":"read_str","setter_type":null,"type":{".class":"CallableType","arg_kinds":[0,0],"arg_names":["self","default"],"arg_types":["jsonschema_path.paths.SchemaPath",{".class":"TypeVarType","default":{".class":"AnyType","missing_import_name":null,"source_any":null,"type_of_any":4},"fullname":"jsonschema_path.paths.TDefault","id":-1,"name":"TDefault","namespace":"jsonschema_path.paths.SchemaPath.read_str#1","upper_bound":"builtins.object","values":[],"variance":0}],"fallback":"builtins.function","from_concatenate":false,"implicit":false,"imprecise_arg_kinds":false,"is_bound":false,"is_ellipsis_args":false,"name":"read_str of SchemaPath","ret_type":{".class":"UnionType","items":["builtins.str",{".class":"TypeVarType","default":{".class":"AnyType","missing_import_name":null,"source_any":null,"type_of_any":4},"fullname":"jsonschema_path.paths.TDefault","id":-1,"name":"TDefault","namespace":"jsonschema_path.paths.SchemaPath.read_str#1","upper_bound":"builtins.object","values":[],"variance":0}],"uses_pep604_syntax":true},"type_guard":null,"type_is":null,"unpack_kwargs":false,"variables":[{".class":"TypeVarType","default":{".class":"AnyType","missing_import_name":null,"source_any":null,"type_of_any":4},"fullname":"jsonschema_path.paths.TDefault","id":-1,"name":"TDefault","namespace":"jsonschema_path.paths.SchemaPath.read_str#1","upper_bound":"builtins.object","values":[],"variance":0}]}}}],"setter_index":null,"type":{".class":"Overloaded","items":[{".class":"CallableType","arg_kinds":[0],"arg_names":["self"],"arg_types":["jsonschema_path.paths.SchemaPath"],"fallback":"builtins.function","from_concatenate":false,"implicit":false,"imprecise_arg_kinds":false,"is_bound":false,"is_ellipsis_args":false,"name":"read_str of SchemaPath","ret_type":"builtins.str","type_guard":null,"type_is":null,"unpack_kwargs":false,"variables":[]},{".class":"CallableType","arg_kinds":[0,0],"arg_names":["self","default"],"arg_types":["jsonschema_path.paths.SchemaPath",{".class":"TypeVarType","default":{".class":"AnyType","missing_import_name":null,"source_any":null,"type_of_any":4},"fullname":"jsonschema_path.paths.TDefault","id":-1,"name":"TDefault","namespace":"jsonschema_path.paths.SchemaPath.read_str#1","upper_bound":"builtins.object","values":[],"variance":0}],"fallback":"builtins.function","from_concatenate":false,"implicit":false,"imprecise_arg_kinds":false,"is_bound":false,"is_ellipsis_args":false,"name":"read_str of SchemaPath","ret_type":{".class":"UnionType","items":["builtins.str",{".class":"TypeVarType","default":{".class":"AnyType","missing_import_name":null,"source_any":null,"type_of_any":4},"fullname":"jsonschema_path.paths.TDefault","id":-1,"name":"TDefault","namespace":"jsonschema_path.paths.SchemaPath.read_str#1","upper_bound":"builtins.object","values":[],"variance":0}],"uses_pep604_syntax":true},"type_guard":null,"type_is":null,"unpack_kwargs":false,"variables":[{".class":"TypeVarType","default":{".class":"AnyType","missing_import_name":null,"source_any":null,"type_of_any":4},"fullname":"jsonschema_path.paths.TDefault","id":-1,"name":"TDefault","namespace":"jsonschema_path.paths.SchemaPath.read_str#1","upper_bound":"builtins.object","values":[],"variance":0}]}]}}},"read_str_or_list":{".class":"SymbolTableNode","kind":"Mdef","node":{".class":"OverloadedFuncDef","deprecated":null,"flags":[],"fullname":"jsonschema_path.paths.SchemaPath.read_str_or_list","impl":{".class":"FuncDef","abstract_status":0,"arg_kinds":[0,1],"arg_names":["self","default"],"dataclass_transform_spec":null,"deprecated":null,"flags":["is_overload","is_trivial_self"],"fullname":"jsonschema_path.paths.SchemaPath.read_str_or_list","name":"read_str_or_list","original_first_arg":"self","type":{".class":"CallableType","arg_kinds":[0,1],"arg_names":["self","default"],"arg_types":["jsonschema_path.paths.SchemaPath","builtins.object"],"fallback":"builtins.function","from_concatenate":false,"implicit":false,"imprecise_arg_kinds":false,"is_bound":false,"is_ellipsis_args":false,"name":"read_str_or_list of SchemaPath","ret_type":"builtins.object","type_guard":null,"type_is":null,"unpack_kwargs":false,"variables":[]}},"items":[{".class":"Decorator","func":{".class":"FuncDef","abstract_status":0,"arg_kinds":[0],"arg_names":["self"],"dataclass_transform_spec":null,"deprecated":null,"flags":["is_overload","is_decorated","is_trivial_self"],"fullname":"jsonschema_path.paths.SchemaPath.read_str_or_list","name":"read_str_or_list","original_first_arg":"self","type":{".class":"CallableType","arg_kinds":[0],"arg_names":["self"],"arg_types":["jsonschema_path.paths.SchemaPath"],"fallback":"builtins.function","from_concatenate":false,"implicit":false,"imprecise_arg_kinds":false,"is_bound":false,"is_ellipsis_args":false,"name":"read_str_or_list of SchemaPath","ret_type":{".class":"UnionType","items":["builtins.str",{".class":"Instance","args":["builtins.str"],"extra_attrs":null,"type_ref":"builtins.list"}],"uses_pep604_syntax":true},"type_guard":null,"type_is":null,"unpack_kwargs":false,"variables":[]}},"is_overload":true,"var":{".class":"Var","flags":["is_ready","is_inferred"],"fullname":"jsonschema_path.paths.SchemaPath.read_str_or_list","name":"read_str_or_list","setter_type":null,"type":{".class":"CallableType","arg_kinds":[0],"arg_names":["self"],"arg_types":["jsonschema_path.paths.SchemaPath"],"fallback":"builtins.function","from_concatenate":false,"implicit":false,"imprecise_arg_kinds":false,"is_bound":false,"is_ellipsis_args":false,"name":"read_str_or_list of SchemaPath","ret_type":{".class":"UnionType","items":["builtins.str",{".class":"Instance","args":["builtins.str"],"extra_attrs":null,"type_ref":"builtins.list"}],"uses_pep604_syntax":true},"type_guard":null,"type_is":null,"unpack_kwargs":false,"variables":[]}}},{".class":"Decorator","func":{".class":"FuncDef","abstract_status":0,"arg_kinds":[0,0],"arg_names":["self","default"],"dataclass_transform_spec":null,"deprecated":null,"flags":["is_overload","is_decorated","is_trivial_self"],"fullname":"jsonschema_path.paths.SchemaPath.read_str_or_list","name":"read_str_or_list","original_first_arg":"self","type":{".class":"CallableType","arg_kinds":[0,0],"arg_names":["self","default"],"arg_types":["jsonschema_path.paths.SchemaPath",{".class":"TypeVarType","default":{".class":"AnyType","missing_import_name":null,"source_any":null,"type_of_any":4},"fullname":"jsonschema_path.paths.TDefault","id":-1,"name":"TDefault","namespace":"jsonschema_path.paths.SchemaPath.read_str_or_list#1","upper_bound":"builtins.object","values":[],"variance":0}],"fallback":"builtins.function","from_concatenate":false,"implicit":false,"imprecise_arg_kinds":false,"is_bound":false,"is_ellipsis_args":false,"name":"read_str_or_list of SchemaPath","ret_type":{".class":"UnionType","items":["builtins.str",{".class":"Instance","args":["builtins.str"],"extra_attrs":null,"type_ref":"builtins.list"},{".class":"TypeVarType","default":{".class":"AnyType","missing_import_name":null,"source_any":null,"type_of_any":4},"fullname":"jsonschema_path.paths.TDefault","id":-1,"name":"TDefault","namespace":"jsonschema_path.paths.SchemaPath.read_str_or_list#1","upper_bound":"builtins.object","values":[],"variance":0}],"uses_pep604_syntax":true},"type_guard":null,"type_is":null,"unpack_kwargs":false,"variables":[{".class":"TypeVarType","default":{".class":"AnyType","missing_import_name":null,"source_any":null,"type_of_any":4},"fullname":"jsonschema_path.paths.TDefault","id":-1,"name":"TDefault","namespace":"jsonschema_path.paths.SchemaPath.read_str_or_list#1","upper_bound":"builtins.object","values":[],"variance":0}]}},"is_overload":true,"var":{".class":"Var","flags":["is_ready","is_inferred"],"fullname":"jsonschema_path.paths.SchemaPath.read_str_or_list","name":"read_str_or_list","setter_type":null,"type":{".class":"CallableType","arg_kinds":[0,0],"arg_names":["self","default"],"arg_types":["jsonschema_path.paths.SchemaPath",{".class":"TypeVarType","default":{".class":"AnyType","missing_import_name":null,"source_any":null,"type_of_any":4},"fullname":"jsonschema_path.paths.TDefault","id":-1,"name":"TDefault","namespace":"jsonschema_path.paths.SchemaPath.read_str_or_list#1","upper_bound":"builtins.object","values":[],"variance":0}],"fallback":"builtins.function","from_concatenate":false,"implicit":false,"imprecise_arg_kinds":false,"is_bound":false,"is_ellipsis_args":false,"name":"read_str_or_list of SchemaPath","ret_type":{".class":"UnionType","items":["builtins.str",{".class":"Instance","args":["builtins.str"],"extra_attrs":null,"type_ref":"builtins.list"},{".class":"TypeVarType","default":{".class":"AnyType","missing_import_name":null,"source_any":null,"type_of_any":4},"fullname":"jsonschema_path.paths.TDefault","id":-1,"name":"TDefault","namespace":"jsonschema_path.paths.SchemaPath.read_str_or_list#1","upper_bound":"builtins.object","values":[],"variance":0}],"uses_pep604_syntax":true},"type_guard":null,"type_is":null,"unpack_kwargs":false,"variables":[{".class":"TypeVarType","default":{".class":"AnyType","missing_import_name":null,"source_any":null,"type_of_any":4},"fullname":"jsonschema_path.paths.TDefault","id":-1,"name":"TDefault","namespace":"jsonschema_path.paths.SchemaPath.read_str_or_list#1","upper_bound":"builtins.object","values":[],"variance":0}]}}}],"setter_index":null,"type":{".class":"Overloaded","items":[{".class":"CallableType","arg_kinds":[0],"arg_names":["self"],"arg_types":["jsonschema_path.paths.SchemaPath"],"fallback":"builtins.function","from_concatenate":false,"implicit":false,"imprecise_arg_kinds":false,"is_bound":false,"is_ellipsis_args":false,"name":"read_str_or_list of SchemaPath","ret_type":{".class":"UnionType","items":["builtins.str",{".class":"Instance","args":["builtins.str"],"extra_attrs":null,"type_ref":"builtins.list"}],"uses_pep604_syntax":true},"type_guard":null,"type_is":null,"unpack_kwargs":false,"variables":[]},{".class":"CallableType","arg_kinds":[0,0],"arg_names":["self","default"],"arg_types":["jsonschema_path.paths.SchemaPath",{".class":"TypeVarType","default":{".class":"AnyType","missing_import_name":null,"source_any":null,"type_of_any":4},"fullname":"jsonschema_path.paths.TDefault","id":-1,"name":"TDefault","namespace":"jsonschema_path.paths.SchemaPath.read_str_or_list#1","upper_bound":"builtins.object","values":[],"variance":0}],"fallback":"builtins.function","from_concatenate":false,"implicit":false,"imprecise_arg_kinds":false,"is_bound":false,"is_ellipsis_args":false,"name":"read_str_or_list of SchemaPath","ret_type":{".class":"UnionType","items":["builtins.str",{".class":"Instance","args":["builtins.str"],"extra_attrs":null,"type_ref":"builtins.list"},{".class":"TypeVarType","default":{".class":"AnyType","missing_import_name":null,"source_any":null,"type_of_any":4},"fullname":"jsonschema_path.paths.TDefault","id":-1,"name":"TDefault","namespace":"jsonschema_path.paths.SchemaPath.read_str_or_list#1","upper_bound":"builtins.object","values":[],"variance":0}],"uses_pep604_syntax":true},"type_guard":null,"type_is":null,"unpack_kwargs":false,"variables":[{".class":"TypeVarType","default":{".class":"AnyType","missing_import_name":null,"source_any":null,"type_of_any":4},"fullname":"jsonschema_path.paths.TDefault","id":-1,"name":"TDefault","namespace":"jsonschema_path.paths.SchemaPath.read_str_or_list#1","upper_bound":"builtins.object","values":[],"variance":0}]}]}}},"resolve":{".class":"SymbolTableNode","kind":"Mdef","node":{".class":"Decorator","func":{".class":"FuncDef","abstract_status":0,"arg_kinds":[0],"arg_names":["self"],"dataclass_transform_spec":null,"deprecated":null,"flags":["is_decorated","is_trivial_self"],"fullname":"jsonschema_path.paths.SchemaPath.resolve","name":"resolve","original_first_arg":"self","type":{".class":"CallableType","arg_kinds":[0],"arg_names":["self"],"arg_types":["jsonschema_path.paths.SchemaPath"],"fallback":"builtins.function","from_concatenate":false,"implicit":false,"imprecise_arg_kinds":false,"is_bound":false,"is_ellipsis_args":false,"name":"resolve of SchemaPath","ret_type":{".class":"Instance","args":[{".class":"Instance","args":[{".class":"TypeAliasType","args":[],"type_ref":"pathable.types.LookupNode"}],"extra_attrs":null,"type_ref":"referencing._core.Resolved"}],"extra_attrs":null,"type_ref":"typing.Iterator"},"type_guard":null,"type_is":null,"unpack_kwargs":false,"variables":[]}},"is_overload":false,"var":{".class":"Var","flags":["is_initialized_in_class","is_ready","is_inferred"],"fullname":"jsonschema_path.paths.SchemaPath.resolve","name":"resolve","setter_type":null,"type":{".class":"CallableType","arg_kinds":[0],"arg_names":["self"],"arg_types":["jsonschema_path.paths.SchemaPath"],"fallback":"builtins.function","from_concatenate":false,"implicit":false,"imprecise_arg_kinds":false,"is_bound":false,"is_ellipsis_args":false,"name":"resolve of SchemaPath","ret_type":{".class":"Instance","args":[{".class":"Instance","args":[{".class":"UnionType","items":[{".class":"Instance","args":[{".class":"TypeAliasType","args":[],"type_ref":"pathable.types.LookupKey"},{".class":"TypeAliasType","args":[],"type_ref":"pathable.types.LookupValue"}],"extra_attrs":null,"type_ref":"pathable.protocols.Subscriptable"},{".class":"TypeAliasType","args":[],"type_ref":"pathable.types.LookupValue"}],"uses_pep604_syntax":true}],"extra_attrs":null,"type_ref":"referencing._core.Resolved"},{".class":"NoneType"},{".class":"NoneType"}],"extra_attrs":null,"type_ref":"contextlib._GeneratorContextManager"},"type_guard":null,"type_is":null,"unpack_kwargs":false,"variables":[]}}}},"str_items":{".class":"SymbolTableNode","kind":"Mdef","node":{".class":"FuncDef","abstract_status":0,"arg_kinds":[0],"arg_names":["self"],"dataclass_transform_spec":null,"deprecated":null,"flags":["is_trivial_self"],"fullname":"jsonschema_path.paths.SchemaPath.str_items","name":"str_items","original_first_arg":"self","type":{".class":"CallableType","arg_kinds":[0],"arg_names":["self"],"arg_types":["jsonschema_path.paths.SchemaPath"],"fallback":"builtins.function","from_concatenate":false,"implicit":false,"imprecise_arg_kinds":false,"is_bound":false,"is_ellipsis_args":false,"name":"str_items of SchemaPath","ret_type":{".class":"Instance","args":[{".class":"TupleType","implicit":false,"items":["builtins.str","jsonschema_path.paths.SchemaPath"],"partial_fallback":{".class":"Instance","args":[{".class":"AnyType","missing_import_name":null,"source_any":null,"type_of_any":6}],"extra_attrs":null,"type_ref":"builtins.tuple"}}],"extra_attrs":null,"type_ref":"typing.Iterator"},"type_guard":null,"type_is":null,"unpack_kwargs":false,"variables":[]}}},"str_keys":{".class":"SymbolTableNode","kind":"Mdef","node":{".class":"FuncDef","abstract_status":0,"arg_kinds":[0],"arg_names":["self"],"dataclass_transform_spec":null,"deprecated":null,"flags":["is_trivial_self"],"fullname":"jsonschema_path.paths.SchemaPath.str_keys","name":"str_keys","original_first_arg":"self","type":{".class":"CallableType","arg_kinds":[0],"arg_names":["self"],"arg_types":["jsonschema_path.paths.SchemaPath"],"fallback":"builtins.function","from_concatenate":false,"implicit":false,"imprecise_arg_kinds":false,"is_bound":false,"is_ellipsis_args":false,"name":"str_keys of SchemaPath","ret_type":{".class":"Instance","args":["builtins.str"],"extra_attrs":null,"type_ref":"typing.Sequence"},"type_guard":null,"type_is":null,"unpack_kwargs":false,"variables":[]}}}},"self_type":{".class":"TypeVarType","default":{".class":"AnyType","missing_import_name":null,"source_any":null,"type_of_any":4},"fullname":"jsonschema_path.paths.SchemaPath.Self","id":0,"name":"Self","namespace":"","upper_bound":"jsonschema_path.paths.SchemaPath","values":[],"variance":0},"slots":null,"tuple_type":null,"type_vars":[],"typeddict_type":null}},"SchemaValue":{".class":"SymbolTableNode","cross_ref":"pathable.types.LookupValue","kind":"Gdef"},"Sequence":{".class":"SymbolTableNode","cross_ref":"typing.Sequence","kind":"Gdef"},"Specification":{".class":"SymbolTableNode","cross_ref":"referencing._core.Specification","kind":"Gdef"},"SupportsRead":{".class":"SymbolTableNode","cross_ref":"jsonschema_path.handlers.protocols.SupportsRead","kind":"Gdef"},"TDefault":{".class":"SymbolTableNode","kind":"Gdef","node":{".class":"TypeVarExpr","default":{".class":"AnyType","missing_import_name":null,"source_any":null,"type_of_any":4},"fullname":"jsonschema_path.paths.TDefault","name":"TDefault","upper_bound":"builtins.object","values":[],"variance":0}},"TSchemaPath":{".class":"SymbolTableNode","kind":"Gdef","node":{".class":"TypeVarExpr","default":{".class":"AnyType","missing_import_name":null,"source_any":null,"type_of_any":4},"fullname":"jsonschema_path.paths.TSchemaPath","name":"TSchemaPath","upper_bound":"jsonschema_path.paths.SchemaPath","values":[],"variance":0}},"TypeVar":{".class":"SymbolTableNode","cross_ref":"typing.TypeVar","kind":"Gdef"},"__annotations__":{".class":"SymbolTableNode","kind":"Gdef","node":{".class":"Var","flags":["is_ready"],"fullname":"jsonschema_path.paths.__annotations__","name":"__annotations__","setter_type":null,"type":{".class":"Instance","args":["builtins.str",{".class":"AnyType","missing_import_name":null,"source_any":null,"type_of_any":6}],"extra_attrs":null,"type_ref":"builtins.dict"}}},"__doc__":{".class":"SymbolTableNode","kind":"Gdef","node":{".class":"Var","flags":["is_ready"],"fullname":"jsonschema_path.paths.__doc__","name":"__doc__","setter_type":null,"type":"builtins.str"}},"__file__":{".class":"SymbolTableNode","kind":"Gdef","node":{".class":"Var","flags":["is_ready"],"fullname":"jsonschema_path.paths.__file__","name":"__file__","setter_type":null,"type":"builtins.str"}},"__name__":{".class":"SymbolTableNode","kind":"Gdef","node":{".class":"Var","flags":["is_ready"],"fullname":"jsonschema_path.paths.__name__","name":"__name__","setter_type":null,"type":"builtins.str"}},"__package__":{".class":"SymbolTableNode","kind":"Gdef","node":{".class":"Var","flags":["is_ready"],"fullname":"jsonschema_path.paths.__package__","name":"__package__","setter_type":null,"type":"builtins.str"}},"__spec__":{".class":"SymbolTableNode","kind":"Gdef","node":{".class":"Var","flags":["is_ready"],"fullname":"jsonschema_path.paths.__spec__","name":"__spec__","setter_type":null,"type":"_frozen_importlib.ModuleSpec"}},"annotations":{".class":"SymbolTableNode","cross_ref":"__future__.annotations","kind":"Gdef"},"cached_property":{".class":"SymbolTableNode","cross_ref":"functools.cached_property","kind":"Gdef"},"contextmanager":{".class":"SymbolTableNode","cross_ref":"contextlib.contextmanager","kind":"Gdef"},"default_handlers":{".class":"SymbolTableNode","cross_ref":"jsonschema_path.handlers.default_handlers","kind":"Gdef"},"is_str_sequence":{".class":"SymbolTableNode","cross_ref":"jsonschema_path.typing.is_str_sequence","kind":"Gdef"},"os":{".class":"SymbolTableNode","cross_ref":"os","kind":"Gdef"},"overload":{".class":"SymbolTableNode","cross_ref":"typing.overload","kind":"Gdef"},"warnings":{".class":"SymbolTableNode","cross_ref":"warnings","kind":"Gdef"}},"path":"/home/ab916/src/clawbridge/.venv/lib/python3.13/site-packages/jsonschema_path/paths.py"}