{".class":"MypyFile","_fullname":"agno.os.routers.database","future_import_flags":[],"is_partial_stub_package":false,"is_stub":false,"names":{".class":"SymbolTable","APIRouter":{".class":"SymbolTableNode","cross_ref":"fastapi.routing.APIRouter","kind":"Gdef"},"AgentOS":{".class":"SymbolTableNode","cross_ref":"agno.os.app.AgentOS","kind":"Gdef"},"AgnoAPISettings":{".class":"SymbolTableNode","cross_ref":"agno.os.settings.AgnoAPISettings","kind":"Gdef"},"AsyncBaseDb":{".class":"SymbolTableNode","cross_ref":"agno.db.base.AsyncBaseDb","kind":"Gdef"},"BadRequestResponse":{".class":"SymbolTableNode","cross_ref":"agno.os.schema.BadRequestResponse","kind":"Gdef"},"Depends":{".class":"SymbolTableNode","cross_ref":"fastapi.param_functions.Depends","kind":"Gdef"},"HTTPException":{".class":"SymbolTableNode","cross_ref":"fastapi.exceptions.HTTPException","kind":"Gdef"},"InternalServerErrorResponse":{".class":"SymbolTableNode","cross_ref":"agno.os.schema.InternalServerErrorResponse","kind":"Gdef"},"JSONResponse":{".class":"SymbolTableNode","cross_ref":"starlette.responses.JSONResponse","kind":"Gdef"},"MigrationManager":{".class":"SymbolTableNode","cross_ref":"agno.db.migrations.manager.MigrationManager","kind":"Gdef"},"NotFoundResponse":{".class":"SymbolTableNode","cross_ref":"agno.os.schema.NotFoundResponse","kind":"Gdef"},"Optional":{".class":"SymbolTableNode","cross_ref":"typing.Optional","kind":"Gdef"},"RemoteDb":{".class":"SymbolTableNode","cross_ref":"agno.remote.base.RemoteDb","kind":"Gdef"},"TYPE_CHECKING":{".class":"SymbolTableNode","cross_ref":"typing.TYPE_CHECKING","kind":"Gdef"},"UnauthenticatedResponse":{".class":"SymbolTableNode","cross_ref":"agno.os.schema.UnauthenticatedResponse","kind":"Gdef"},"ValidationErrorResponse":{".class":"SymbolTableNode","cross_ref":"agno.os.schema.ValidationErrorResponse","kind":"Gdef"},"__annotations__":{".class":"SymbolTableNode","kind":"Gdef","node":{".class":"Var","flags":["is_ready"],"fullname":"agno.os.routers.database.__annotations__","name":"__annotations__","setter_type":null,"type":{".class":"Instance","args":["builtins.str",{".class":"AnyType","missing_import_name":null,"source_any":null,"type_of_any":6}],"extra_attrs":null,"type_ref":"builtins.dict"}}},"__doc__":{".class":"SymbolTableNode","kind":"Gdef","node":{".class":"Var","flags":["is_ready"],"fullname":"agno.os.routers.database.__doc__","name":"__doc__","setter_type":null,"type":"builtins.str"}},"__file__":{".class":"SymbolTableNode","kind":"Gdef","node":{".class":"Var","flags":["is_ready"],"fullname":"agno.os.routers.database.__file__","name":"__file__","setter_type":null,"type":"builtins.str"}},"__name__":{".class":"SymbolTableNode","kind":"Gdef","node":{".class":"Var","flags":["is_ready"],"fullname":"agno.os.routers.database.__name__","name":"__name__","setter_type":null,"type":"builtins.str"}},"__package__":{".class":"SymbolTableNode","kind":"Gdef","node":{".class":"Var","flags":["is_ready"],"fullname":"agno.os.routers.database.__package__","name":"__package__","setter_type":null,"type":"builtins.str"}},"__spec__":{".class":"SymbolTableNode","kind":"Gdef","node":{".class":"Var","flags":["is_ready"],"fullname":"agno.os.routers.database.__spec__","name":"__spec__","setter_type":null,"type":"_frozen_importlib.ModuleSpec"}},"get_authentication_dependency":{".class":"SymbolTableNode","cross_ref":"agno.os.auth.get_authentication_dependency","kind":"Gdef"},"get_database_router":{".class":"SymbolTableNode","kind":"Gdef","node":{".class":"FuncDef","abstract_status":0,"arg_kinds":[0,1],"arg_names":["os","settings"],"dataclass_transform_spec":null,"deprecated":null,"flags":[],"fullname":"agno.os.routers.database.get_database_router","name":"get_database_router","original_first_arg":"os","type":{".class":"CallableType","arg_kinds":[0,1],"arg_names":["os","settings"],"arg_types":["agno.os.app.AgentOS","agno.os.settings.AgnoAPISettings"],"fallback":"builtins.function","from_concatenate":false,"implicit":false,"imprecise_arg_kinds":false,"is_bound":false,"is_ellipsis_args":false,"name":"get_database_router","ret_type":"fastapi.routing.APIRouter","type_guard":null,"type_is":null,"unpack_kwargs":false,"variables":[]}}},"get_db":{".class":"SymbolTableNode","cross_ref":"agno.os.utils.get_db","kind":"Gdef"},"log_info":{".class":"SymbolTableNode","cross_ref":"agno.utils.log.log_info","kind":"Gdef"},"version":{".class":"SymbolTableNode","cross_ref":"packaging.version","kind":"Gdef"}},"path":"/home/ab916/src/clawbridge/.venv/lib/python3.13/site-packages/agno/os/routers/database.py"}